{
 "updated": "2026-07-06 12:24:00",
 "quotes": {
  "0050": {
   "market": "TWSE",
   "price": 108.5,
   "pct1": 0.14,
   "amount": 64.17
  },
  "1216": {
   "market": "TWSE",
   "price": 77.8,
   "pct1": 1.97,
   "amount": 13.54
  },
  "1301": {
   "market": "TWSE",
   "price": 60.9,
   "pct1": -1.93,
   "amount": 33.88
  },
  "1303": {
   "market": "TWSE",
   "price": 189.0,
   "pct1": -4.06,
   "amount": 31.03
  },
  "1409": {
   "market": "TWSE",
   "price": 30.15,
   "pct1": -2.74,
   "amount": 36.92
  },
  "1417": {
   "market": "TWSE",
   "price": 9.14,
   "pct1": 0.22,
   "amount": 0.04
  },
  "1466": {
   "market": "TWSE",
   "price": 18.2,
   "pct1": -1.09,
   "amount": 0.84
  },
  "1474": {
   "market": "TWSE",
   "price": 10.85,
   "pct1": -4.41,
   "amount": 0.11
  },
  "1476": {
   "market": "TWSE",
   "price": 324.0,
   "pct1": 0.15,
   "amount": 2.09
  },
  "1503": {
   "market": "TWSE",
   "price": 242.5,
   "pct1": 1.89,
   "amount": 8.37
  },
  "1504": {
   "market": "TWSE",
   "price": 73.6,
   "pct1": 5.14,
   "amount": 17.99
  },
  "1513": {
   "market": "TWSE",
   "price": 179.5,
   "pct1": 1.7,
   "amount": 10.2
  },
  "1514": {
   "market": "TWSE",
   "price": 128.0,
   "pct1": 4.07,
   "amount": 15.75
  },
  "1519": {
   "market": "TWSE",
   "price": 776.0,
   "pct1": 0.39,
   "amount": 17.53
  },
  "1536": {
   "market": "TWSE",
   "price": 53.0,
   "pct1": 1.53,
   "amount": 2.02
  },
  "1560": {
   "market": "TWSE",
   "price": 744.0,
   "pct1": -1.59,
   "amount": 3.0
  },
  "1590": {
   "market": "TWSE",
   "price": 1400.0,
   "pct1": -2.78,
   "amount": 7.11
  },
  "1597": {
   "market": "TWSE",
   "price": 152.0,
   "pct1": -2.56,
   "amount": 1.64
  },
  "1603": {
   "market": "TWSE",
   "price": 32.8,
   "pct1": 0.61,
   "amount": 0.09
  },
  "1604": {
   "market": "TWSE",
   "price": 23.7,
   "pct1": 0.85,
   "amount": 0.16
  },
  "1605": {
   "market": "TWSE",
   "price": 36.95,
   "pct1": 1.93,
   "amount": 8.68
  },
  "1609": {
   "market": "TWSE",
   "price": 43.75,
   "pct1": 9.92,
   "amount": 11.59
  },
  "1611": {
   "market": "TWSE",
   "price": 13.9,
   "pct1": 0.72,
   "amount": 0.22
  },
  "1612": {
   "market": "TWSE",
   "price": 35.2,
   "pct1": 0.28,
   "amount": 0.27
  },
  "1615": {
   "market": "TWSE",
   "price": 45.45,
   "pct1": 0.55,
   "amount": 0.04
  },
  "1626": {
   "market": "TWSE",
   "price": 11.3,
   "pct1": 0.89,
   "amount": 0.02
  },
  "1784": {
   "market": "TPEX",
   "price": 70.9,
   "pct1": 1.58,
   "amount": 0.21
  },
  "1815": {
   "market": "TPEX",
   "price": 100.0,
   "pct1": -1.48,
   "amount": 12.57
  },
  "2002": {
   "market": "TWSE",
   "price": 18.95,
   "pct1": 0.0,
   "amount": 3.51
  },
  "2049": {
   "market": "TWSE",
   "price": 356.5,
   "pct1": 1.86,
   "amount": 11.76
  },
  "2059": {
   "market": "TWSE",
   "price": 7760.0,
   "pct1": -3.0,
   "amount": 26.39
  },
  "2207": {
   "market": "TWSE",
   "price": 479.0,
   "pct1": 1.27,
   "amount": 0.75
  },
  "2208": {
   "market": "TWSE",
   "price": 20.55,
   "pct1": -1.2,
   "amount": 5.22
  },
  "2231": {
   "market": "TWSE",
   "price": 123.0,
   "pct1": 3.8,
   "amount": 4.67
  },
  "2233": {
   "market": "TWSE",
   "price": 267.5,
   "pct1": -2.73,
   "amount": 2.48
  },
  "2236": {
   "market": "TWSE",
   "price": 186.0,
   "pct1": 1.09,
   "amount": 2.23
  },
  "2301": {
   "market": "TWSE",
   "price": 226.0,
   "pct1": 3.2,
   "amount": 44.01
  },
  "2303": {
   "market": "TWSE",
   "price": 165.5,
   "pct1": -2.93,
   "amount": 64.12
  },
  "2308": {
   "market": "TWSE",
   "price": 2010.0,
   "pct1": -3.13,
   "amount": 131.18
  },
  "2313": {
   "market": "TWSE",
   "price": 232.5,
   "pct1": 1.31,
   "amount": 59.94
  },
  "2317": {
   "market": "TWSE",
   "price": 242.0,
   "pct1": 0.62,
   "amount": 81.29
  },
  "2324": {
   "market": "TWSE",
   "price": 35.8,
   "pct1": 2.43,
   "amount": 15.53
  },
  "2327": {
   "market": "TWSE",
   "price": 1015.0,
   "pct1": -2.87,
   "amount": 340.36
  },
  "2329": {
   "market": "TWSE",
   "price": 55.1,
   "pct1": 3.96,
   "amount": 4.52
  },
  "2330": {
   "market": "TWSE",
   "price": 2480.0,
   "pct1": 1.43,
   "amount": 354.93
  },
  "2337": {
   "market": "TWSE",
   "price": 145.5,
   "pct1": 2.11,
   "amount": 72.16
  },
  "2344": {
   "market": "TWSE",
   "price": 187.0,
   "pct1": 1.36,
   "amount": 236.85
  },
  "2345": {
   "market": "TWSE",
   "price": 2665.0,
   "pct1": -2.56,
   "amount": 47.56
  },
  "2353": {
   "market": "TWSE",
   "price": 32.75,
   "pct1": -0.46,
   "amount": 6.91
  },
  "2355": {
   "market": "TWSE",
   "price": 53.0,
   "pct1": -0.19,
   "amount": 1.63
  },
  "2356": {
   "market": "TWSE",
   "price": 68.1,
   "pct1": 0.74,
   "amount": 12.79
  },
  "2357": {
   "market": "TWSE",
   "price": 680.0,
   "pct1": 0.74,
   "amount": 16.17
  },
  "2359": {
   "market": "TWSE",
   "price": 144.5,
   "pct1": 1.76,
   "amount": 5.03
  },
  "2360": {
   "market": "TWSE",
   "price": 2190.0,
   "pct1": -3.31,
   "amount": 22.7
  },
  "2367": {
   "market": "TWSE",
   "price": 53.9,
   "pct1": -2.0,
   "amount": 3.79
  },
  "2368": {
   "market": "TWSE",
   "price": 1220.0,
   "pct1": -6.51,
   "amount": 51.76
  },
  "2371": {
   "market": "TWSE",
   "price": 28.45,
   "pct1": 1.61,
   "amount": 2.8
  },
  "2375": {
   "market": "TWSE",
   "price": 212.0,
   "pct1": -1.85,
   "amount": 24.59
  },
  "2376": {
   "market": "TWSE",
   "price": 338.5,
   "pct1": 0.0,
   "amount": 9.54
  },
  "2377": {
   "market": "TWSE",
   "price": 144.0,
   "pct1": 0.7,
   "amount": 10.51
  },
  "2379": {
   "market": "TWSE",
   "price": 792.0,
   "pct1": 1.15,
   "amount": 15.55
  },
  "2382": {
   "market": "TWSE",
   "price": 382.0,
   "pct1": 1.33,
   "amount": 70.33
  },
  "2383": {
   "market": "TWSE",
   "price": 5475.0,
   "pct1": -9.95,
   "amount": 177.28
  },
  "2395": {
   "market": "TWSE",
   "price": 513.0,
   "pct1": -1.54,
   "amount": 5.07
  },
  "2397": {
   "market": "TWSE",
   "price": 61.3,
   "pct1": 0.33,
   "amount": 0.28
  },
  "2401": {
   "market": "TWSE",
   "price": 33.15,
   "pct1": -0.9,
   "amount": 2.35
  },
  "2404": {
   "market": "TWSE",
   "price": 1320.0,
   "pct1": -2.22,
   "amount": 25.07
  },
  "2408": {
   "market": "TWSE",
   "price": 429.0,
   "pct1": 4.76,
   "amount": 200.09
  },
  "2409": {
   "market": "TWSE",
   "price": 31.5,
   "pct1": 5.0,
   "amount": 95.0
  },
  "2412": {
   "market": "TWSE",
   "price": 142.0,
   "pct1": 0.71,
   "amount": 10.14
  },
  "2413": {
   "market": "TWSE",
   "price": 48.55,
   "pct1": 0.21,
   "amount": 0.44
  },
  "2419": {
   "market": "TWSE",
   "price": 29.35,
   "pct1": -1.18,
   "amount": 0.51
  },
  "2421": {
   "market": "TWSE",
   "price": 148.5,
   "pct1": -0.34,
   "amount": 1.47
  },
  "2428": {
   "market": "TWSE",
   "price": 346.5,
   "pct1": 1.32,
   "amount": 17.26
  },
  "2429": {
   "market": "TWSE",
   "price": 50.8,
   "pct1": 4.31,
   "amount": 1.17
  },
  "2436": {
   "market": "TWSE",
   "price": 78.7,
   "pct1": 3.69,
   "amount": 5.61
  },
  "2449": {
   "market": "TWSE",
   "price": 355.0,
   "pct1": 5.97,
   "amount": 157.37
  },
  "2451": {
   "market": "TWSE",
   "price": 271.0,
   "pct1": 3.04,
   "amount": 8.48
  },
  "2453": {
   "market": "TWSE",
   "price": 57.6,
   "pct1": 0.35,
   "amount": 0.21
  },
  "2454": {
   "market": "TWSE",
   "price": 4195.0,
   "pct1": 0.0,
   "amount": 202.42
  },
  "2455": {
   "market": "TWSE",
   "price": 339.5,
   "pct1": -5.17,
   "amount": 32.2
  },
  "2458": {
   "market": "TWSE",
   "price": 178.5,
   "pct1": -2.99,
   "amount": 8.41
  },
  "2464": {
   "market": "TWSE",
   "price": 169.5,
   "pct1": -1.74,
   "amount": 16.88
  },
  "2467": {
   "market": "TWSE",
   "price": 641.0,
   "pct1": 4.23,
   "amount": 11.06
  },
  "2471": {
   "market": "TWSE",
   "price": 54.0,
   "pct1": 0.19,
   "amount": 0.07
  },
  "2472": {
   "market": "TWSE",
   "price": 406.0,
   "pct1": -4.47,
   "amount": 26.9
  },
  "2474": {
   "market": "TWSE",
   "price": 196.5,
   "pct1": -5.07,
   "amount": 16.06
  },
  "2478": {
   "market": "TWSE",
   "price": 216.0,
   "pct1": -9.24,
   "amount": 23.06
  },
  "2480": {
   "market": "TWSE",
   "price": 163.5,
   "pct1": 2.51,
   "amount": 1.02
  },
  "2481": {
   "market": "TWSE",
   "price": 227.5,
   "pct1": 9.9,
   "amount": 18.33
  },
  "2489": {
   "market": "TWSE",
   "price": 41.45,
   "pct1": -0.6,
   "amount": 2.72
  },
  "2492": {
   "market": "TWSE",
   "price": 550.0,
   "pct1": -2.31,
   "amount": 6.38
  },
  "2603": {
   "market": "TWSE",
   "price": 196.0,
   "pct1": 0.51,
   "amount": 12.84
  },
  "2609": {
   "market": "TWSE",
   "price": 53.2,
   "pct1": 1.53,
   "amount": 7.6
  },
  "2610": {
   "market": "TWSE",
   "price": 22.6,
   "pct1": 0.22,
   "amount": 4.53
  },
  "2615": {
   "market": "TWSE",
   "price": 79.5,
   "pct1": -3.99,
   "amount": 7.3
  },
  "2618": {
   "market": "TWSE",
   "price": 43.9,
   "pct1": 0.11,
   "amount": 11.21
  },
  "2630": {
   "market": "TWSE",
   "price": 57.0,
   "pct1": 2.15,
   "amount": 15.18
  },
  "2634": {
   "market": "TWSE",
   "price": 61.4,
   "pct1": 2.33,
   "amount": 44.5
  },
  "2637": {
   "market": "TWSE",
   "price": 78.2,
   "pct1": 5.25,
   "amount": 2.3
  },
  "2644": {
   "market": "TPEX",
   "price": 86.0,
   "pct1": -0.12,
   "amount": 0.09
  },
  "2645": {
   "market": "TWSE",
   "price": 238.0,
   "pct1": 9.93,
   "amount": 30.16
  },
  "2706": {
   "market": "TWSE",
   "price": 12.7,
   "pct1": 0.4,
   "amount": 0.01
  },
  "2723": {
   "market": "TWSE",
   "price": 67.9,
   "pct1": 0.74,
   "amount": 0.1
  },
  "2727": {
   "market": "TWSE",
   "price": 246.5,
   "pct1": 0.61,
   "amount": 0.56
  },
  "2731": {
   "market": "TWSE",
   "price": 150.0,
   "pct1": 0.0,
   "amount": 0.49
  },
  "2881": {
   "market": "TWSE",
   "price": 121.0,
   "pct1": 0.0,
   "amount": 11.49
  },
  "2882": {
   "market": "TWSE",
   "price": 93.5,
   "pct1": -0.11,
   "amount": 19.36
  },
  "2884": {
   "market": "TWSE",
   "price": 34.25,
   "pct1": 1.63,
   "amount": 6.58
  },
  "2886": {
   "market": "TWSE",
   "price": 46.45,
   "pct1": 2.09,
   "amount": 5.91
  },
  "2891": {
   "market": "TWSE",
   "price": 71.3,
   "pct1": 0.99,
   "amount": 12.76
  },
  "2912": {
   "market": "TWSE",
   "price": 241.0,
   "pct1": 4.33,
   "amount": 8.28
  },
  "2929": {
   "market": "TWSE",
   "price": 5.84,
   "pct1": -0.17,
   "amount": 0.01
  },
  "2949": {
   "market": "TPEX",
   "price": 72.9,
   "pct1": 2.82,
   "amount": 0.01
  },
  "3005": {
   "market": "TWSE",
   "price": 110.0,
   "pct1": 2.8,
   "amount": 7.43
  },
  "3006": {
   "market": "TWSE",
   "price": 221.5,
   "pct1": 4.73,
   "amount": 23.79
  },
  "3008": {
   "market": "TWSE",
   "price": 4120.0,
   "pct1": -2.6,
   "amount": 66.79
  },
  "3013": {
   "market": "TWSE",
   "price": 109.5,
   "pct1": -1.79,
   "amount": 0.9
  },
  "3014": {
   "market": "TWSE",
   "price": 158.0,
   "pct1": -1.25,
   "amount": 2.11
  },
  "3016": {
   "market": "TWSE",
   "price": 128.5,
   "pct1": -5.17,
   "amount": 20.73
  },
  "3017": {
   "market": "TWSE",
   "price": 2715.0,
   "pct1": -1.63,
   "amount": 78.99
  },
  "3022": {
   "market": "TWSE",
   "price": 87.5,
   "pct1": 0.46,
   "amount": 2.47
  },
  "3024": {
   "market": "TWSE",
   "price": 12.45,
   "pct1": -0.4,
   "amount": 0.1
  },
  "3026": {
   "market": "TWSE",
   "price": 975.0,
   "pct1": -1.32,
   "amount": 151.21
  },
  "3027": {
   "market": "TWSE",
   "price": 22.65,
   "pct1": 2.95,
   "amount": 0.22
  },
  "3029": {
   "market": "TWSE",
   "price": 105.0,
   "pct1": 2.44,
   "amount": 1.69
  },
  "3030": {
   "market": "TWSE",
   "price": 311.5,
   "pct1": -3.11,
   "amount": 6.22
  },
  "3032": {
   "market": "TWSE",
   "price": 79.7,
   "pct1": 0.89,
   "amount": 0.25
  },
  "3034": {
   "market": "TWSE",
   "price": 538.0,
   "pct1": 0.0,
   "amount": 9.51
  },
  "3035": {
   "market": "TWSE",
   "price": 212.5,
   "pct1": -4.49,
   "amount": 13.15
  },
  "3036": {
   "market": "TWSE",
   "price": 216.5,
   "pct1": -2.26,
   "amount": 10.68
  },
  "3037": {
   "market": "TWSE",
   "price": 927.0,
   "pct1": -4.33,
   "amount": 187.96
  },
  "3044": {
   "market": "TWSE",
   "price": 505.0,
   "pct1": -2.88,
   "amount": 9.33
  },
  "3060": {
   "market": "TWSE",
   "price": 37.6,
   "pct1": 5.77,
   "amount": 1.59
  },
  "3081": {
   "market": "TPEX",
   "price": 2050.0,
   "pct1": -2.38,
   "amount": 30.26
  },
  "3088": {
   "market": "TPEX",
   "price": 144.5,
   "pct1": -1.37,
   "amount": 1.34
  },
  "3105": {
   "market": "TPEX",
   "price": 419.0,
   "pct1": 1.95,
   "amount": 58.4
  },
  "3122": {
   "market": "TPEX",
   "price": 31.35,
   "pct1": -2.03,
   "amount": 0.06
  },
  "3131": {
   "market": "TPEX",
   "price": 3440.0,
   "pct1": -9.11,
   "amount": 15.29
  },
  "3163": {
   "market": "TPEX",
   "price": 817.0,
   "pct1": -0.12,
   "amount": 21.2
  },
  "3167": {
   "market": "TWSE",
   "price": 903.0,
   "pct1": 2.96,
   "amount": 56.83
  },
  "3189": {
   "market": "TWSE",
   "price": 783.0,
   "pct1": -6.0,
   "amount": 20.16
  },
  "3231": {
   "market": "TWSE",
   "price": 159.0,
   "pct1": 0.0,
   "amount": 28.69
  },
  "3260": {
   "market": "TPEX",
   "price": 412.5,
   "pct1": 0.24,
   "amount": 21.72
  },
  "3324": {
   "market": "TPEX",
   "price": 1020.0,
   "pct1": 0.0,
   "amount": 7.17
  },
  "3357": {
   "market": "TPEX",
   "price": 287.0,
   "pct1": -1.71,
   "amount": 7.13
  },
  "3363": {
   "market": "TPEX",
   "price": 584.0,
   "pct1": 0.52,
   "amount": 29.82
  },
  "3376": {
   "market": "TWSE",
   "price": 200.0,
   "pct1": -2.2,
   "amount": 5.33
  },
  "3402": {
   "market": "TPEX",
   "price": 156.5,
   "pct1": 0.97,
   "amount": 3.26
  },
  "3413": {
   "market": "TWSE",
   "price": 324.5,
   "pct1": -0.61,
   "amount": 4.31
  },
  "3416": {
   "market": "TWSE",
   "price": 186.0,
   "pct1": -0.53,
   "amount": 1.2
  },
  "3443": {
   "market": "TWSE",
   "price": 4650.0,
   "pct1": -7.74,
   "amount": 94.07
  },
  "3450": {
   "market": "TWSE",
   "price": 533.0,
   "pct1": 0.57,
   "amount": 6.43
  },
  "3479": {
   "market": "TPEX",
   "price": 143.5,
   "pct1": 0.35,
   "amount": 2.17
  },
  "3481": {
   "market": "TWSE",
   "price": 69.4,
   "pct1": 5.15,
   "amount": 299.79
  },
  "3483": {
   "market": "TPEX",
   "price": 93.3,
   "pct1": 0.32,
   "amount": 0.31
  },
  "3491": {
   "market": "TPEX",
   "price": 1295.0,
   "pct1": -3.36,
   "amount": 13.09
  },
  "3515": {
   "market": "TWSE",
   "price": 217.0,
   "pct1": 1.17,
   "amount": 0.74
  },
  "3530": {
   "market": "TWSE",
   "price": 69.7,
   "pct1": 0.0,
   "amount": 0.1
  },
  "3551": {
   "market": "TPEX",
   "price": 210.5,
   "pct1": 2.18,
   "amount": 1.9
  },
  "3556": {
   "market": "TPEX",
   "price": 72.9,
   "pct1": 0.83,
   "amount": 0.48
  },
  "3558": {
   "market": "TPEX",
   "price": 134.5,
   "pct1": 0.0,
   "amount": 0.13
  },
  "3564": {
   "market": "TPEX",
   "price": 54.8,
   "pct1": 9.93,
   "amount": 0.12
  },
  "3583": {
   "market": "TWSE",
   "price": 853.0,
   "pct1": 0.24,
   "amount": 8.71
  },
  "3594": {
   "market": "TPEX",
   "price": 54.7,
   "pct1": -6.81,
   "amount": 1.02
  },
  "3596": {
   "market": "TWSE",
   "price": 196.5,
   "pct1": -0.51,
   "amount": 2.85
  },
  "3653": {
   "market": "TWSE",
   "price": 3370.0,
   "pct1": -1.46,
   "amount": 14.89
  },
  "3661": {
   "market": "TWSE",
   "price": 4305.0,
   "pct1": -7.42,
   "amount": 72.03
  },
  "3665": {
   "market": "TWSE",
   "price": 1965.0,
   "pct1": -1.5,
   "amount": 31.18
  },
  "3673": {
   "market": "TWSE",
   "price": 83.0,
   "pct1": 0.73,
   "amount": 6.82
  },
  "3680": {
   "market": "TPEX",
   "price": 537.0,
   "pct1": -0.37,
   "amount": 9.62
  },
  "3686": {
   "market": "TWSE",
   "price": 17.3,
   "pct1": 0.0,
   "amount": 0.03
  },
  "3693": {
   "market": "TPEX",
   "price": 501.0,
   "pct1": -1.18,
   "amount": 1.54
  },
  "3702": {
   "market": "TWSE",
   "price": 111.0,
   "pct1": 0.91,
   "amount": 6.2
  },
  "3704": {
   "market": "TWSE",
   "price": 45.35,
   "pct1": -3.41,
   "amount": 1.44
  },
  "3706": {
   "market": "TWSE",
   "price": 90.9,
   "pct1": -0.11,
   "amount": 11.47
  },
  "3707": {
   "market": "TPEX",
   "price": 86.7,
   "pct1": -4.73,
   "amount": 23.93
  },
  "3711": {
   "market": "TWSE",
   "price": 689.0,
   "pct1": 1.03,
   "amount": 124.0
  },
  "4540": {
   "market": "TWSE",
   "price": 64.0,
   "pct1": 0.0,
   "amount": 2.05
  },
  "4541": {
   "market": "TPEX",
   "price": 66.7,
   "pct1": 9.88,
   "amount": 8.85
  },
  "4576": {
   "market": "TWSE",
   "price": 229.5,
   "pct1": 3.15,
   "amount": 4.65
  },
  "4585": {
   "market": "TWSE",
   "price": 331.5,
   "pct1": -2.64,
   "amount": 1.5
  },
  "4749": {
   "market": "TPEX",
   "price": 919.0,
   "pct1": 0.66,
   "amount": 12.04
  },
  "4763": {
   "market": "TWSE",
   "price": 50.3,
   "pct1": -1.95,
   "amount": 5.14
  },
  "4772": {
   "market": "TPEX",
   "price": 284.0,
   "pct1": 1.07,
   "amount": 3.11
  },
  "4906": {
   "market": "TWSE",
   "price": 43.15,
   "pct1": -1.26,
   "amount": 2.64
  },
  "4916": {
   "market": "TWSE",
   "price": 113.5,
   "pct1": -1.3,
   "amount": 7.33
  },
  "4919": {
   "market": "TWSE",
   "price": 177.5,
   "pct1": 0.57,
   "amount": 16.99
  },
  "4938": {
   "market": "TWSE",
   "price": 84.3,
   "pct1": 0.84,
   "amount": 8.61
  },
  "4943": {
   "market": "TWSE",
   "price": 9.0,
   "pct1": 0.0,
   "amount": 0.0
  },
  "4952": {
   "market": "TWSE",
   "price": 59.3,
   "pct1": -1.33,
   "amount": 0.61
  },
  "4953": {
   "market": "TPEX",
   "price": 130.5,
   "pct1": 1.95,
   "amount": 0.58
  },
  "4958": {
   "market": "TWSE",
   "price": 586.0,
   "pct1": -4.4,
   "amount": 163.74
  },
  "4961": {
   "market": "TWSE",
   "price": 177.5,
   "pct1": 2.6,
   "amount": 2.46
  },
  "4966": {
   "market": "TPEX",
   "price": 624.0,
   "pct1": -4.59,
   "amount": 7.9
  },
  "4967": {
   "market": "TWSE",
   "price": 261.0,
   "pct1": 0.38,
   "amount": 6.96
  },
  "4971": {
   "market": "TPEX",
   "price": 480.5,
   "pct1": -3.51,
   "amount": 2.55
  },
  "4977": {
   "market": "TWSE",
   "price": 159.5,
   "pct1": -1.54,
   "amount": 1.48
  },
  "4979": {
   "market": "TPEX",
   "price": 456.5,
   "pct1": -2.56,
   "amount": 20.13
  },
  "5222": {
   "market": "TWSE",
   "price": 130.0,
   "pct1": 1.96,
   "amount": 1.44
  },
  "5258": {
   "market": "TWSE",
   "price": 52.0,
   "pct1": 0.0,
   "amount": 0.22
  },
  "5269": {
   "market": "TWSE",
   "price": 1535.0,
   "pct1": 0.33,
   "amount": 11.36
  },
  "5274": {
   "market": "TPEX",
   "price": 16105.0,
   "pct1": -6.72,
   "amount": 30.57
  },
  "5285": {
   "market": "TWSE",
   "price": 106.5,
   "pct1": 9.91,
   "amount": 7.71
  },
  "5289": {
   "market": "TPEX",
   "price": 1655.0,
   "pct1": 1.22,
   "amount": 35.26
  },
  "5299": {
   "market": "TPEX",
   "price": 141.5,
   "pct1": 9.69,
   "amount": 4.33
  },
  "5302": {
   "market": "TPEX",
   "price": 15.45,
   "pct1": 9.96,
   "amount": 0.5
  },
  "5328": {
   "market": "TPEX",
   "price": 81.7,
   "pct1": -0.85,
   "amount": 20.84
  },
  "5340": {
   "market": "TPEX",
   "price": 89.0,
   "pct1": -1.22,
   "amount": 0.6
  },
  "5347": {
   "market": "TPEX",
   "price": 185.5,
   "pct1": -4.13,
   "amount": 34.26
  },
  "5371": {
   "market": "TPEX",
   "price": 102.0,
   "pct1": 9.56,
   "amount": 55.18
  },
  "5388": {
   "market": "TWSE",
   "price": 81.6,
   "pct1": 0.0,
   "amount": 1.22
  },
  "5439": {
   "market": "TPEX",
   "price": 347.5,
   "pct1": -1.0,
   "amount": 8.0
  },
  "5443": {
   "market": "TPEX",
   "price": 120.5,
   "pct1": -0.41,
   "amount": 1.98
  },
  "5471": {
   "market": "TWSE",
   "price": 63.7,
   "pct1": 1.92,
   "amount": 3.75
  },
  "5474": {
   "market": "TPEX",
   "price": 174.0,
   "pct1": 2.05,
   "amount": 0.52
  },
  "5536": {
   "market": "TPEX",
   "price": 1420.0,
   "pct1": -0.7,
   "amount": 8.1
  },
  "5706": {
   "market": "TWSE",
   "price": 48.15,
   "pct1": 0.42,
   "amount": 0.06
  },
  "5871": {
   "market": "TWSE",
   "price": 115.5,
   "pct1": -0.86,
   "amount": 4.28
  },
  "5903": {
   "market": "TPEX",
   "price": 188.0,
   "pct1": -0.27,
   "amount": 0.05
  },
  "6112": {
   "market": "TWSE",
   "price": 45.05,
   "pct1": 0.78,
   "amount": 0.16
  },
  "6116": {
   "market": "TWSE",
   "price": 18.35,
   "pct1": 1.1,
   "amount": 7.29
  },
  "6117": {
   "market": "TWSE",
   "price": 74.2,
   "pct1": -0.27,
   "amount": 0.07
  },
  "6121": {
   "market": "TPEX",
   "price": 467.5,
   "pct1": 10.0,
   "amount": 7.17
  },
  "6125": {
   "market": "TPEX",
   "price": 60.4,
   "pct1": 1.17,
   "amount": 0.55
  },
  "6128": {
   "market": "TWSE",
   "price": 20.7,
   "pct1": -0.48,
   "amount": 0.02
  },
  "6129": {
   "market": "TPEX",
   "price": 20.6,
   "pct1": 7.57,
   "amount": 0.82
  },
  "6138": {
   "market": "TPEX",
   "price": 440.0,
   "pct1": 10.0,
   "amount": 13.51
  },
  "6139": {
   "market": "TWSE",
   "price": 948.0,
   "pct1": 0.0,
   "amount": 27.16
  },
  "6146": {
   "market": "TPEX",
   "price": 198.5,
   "pct1": 1.79,
   "amount": 0.62
  },
  "6147": {
   "market": "TPEX",
   "price": 219.0,
   "pct1": 1.62,
   "amount": 77.05
  },
  "6155": {
   "market": "TWSE",
   "price": 83.9,
   "pct1": -3.56,
   "amount": 2.02
  },
  "6163": {
   "market": "TPEX",
   "price": 49.1,
   "pct1": 1.55,
   "amount": 1.12
  },
  "6166": {
   "market": "TWSE",
   "price": 132.0,
   "pct1": -1.49,
   "amount": 0.76
  },
  "6168": {
   "market": "TWSE",
   "price": 30.15,
   "pct1": 0.84,
   "amount": 0.78
  },
  "6173": {
   "market": "TPEX",
   "price": 318.0,
   "pct1": -9.27,
   "amount": 43.07
  },
  "6182": {
   "market": "TPEX",
   "price": 162.5,
   "pct1": -0.31,
   "amount": 235.59
  },
  "6187": {
   "market": "TPEX",
   "price": 1040.0,
   "pct1": 0.97,
   "amount": 25.04
  },
  "6188": {
   "market": "TPEX",
   "price": 80.4,
   "pct1": 0.12,
   "amount": 1.43
  },
  "6196": {
   "market": "TWSE",
   "price": 574.0,
   "pct1": -2.38,
   "amount": 7.24
  },
  "6202": {
   "market": "TWSE",
   "price": 69.5,
   "pct1": 3.73,
   "amount": 5.98
  },
  "6206": {
   "market": "TWSE",
   "price": 134.5,
   "pct1": 1.51,
   "amount": 0.74
  },
  "6213": {
   "market": "TWSE",
   "price": 390.0,
   "pct1": -1.02,
   "amount": 98.64
  },
  "6214": {
   "market": "TWSE",
   "price": 135.5,
   "pct1": 1.5,
   "amount": 1.2
  },
  "6223": {
   "market": "TPEX",
   "price": 6985.0,
   "pct1": -5.35,
   "amount": 31.24
  },
  "6239": {
   "market": "TWSE",
   "price": 346.0,
   "pct1": 2.37,
   "amount": 123.44
  },
  "6244": {
   "market": "TPEX",
   "price": 27.7,
   "pct1": 1.84,
   "amount": 0.75
  },
  "6245": {
   "market": "TPEX",
   "price": 81.8,
   "pct1": 0.0,
   "amount": 0.36
  },
  "6263": {
   "market": "TPEX",
   "price": 167.5,
   "pct1": -0.3,
   "amount": 0.67
  },
  "6271": {
   "market": "TWSE",
   "price": 279.5,
   "pct1": 0.18,
   "amount": 65.37
  },
  "6274": {
   "market": "TPEX",
   "price": 1640.0,
   "pct1": -8.38,
   "amount": 108.05
  },
  "6278": {
   "market": "TWSE",
   "price": 207.5,
   "pct1": -2.12,
   "amount": 15.26
  },
  "6282": {
   "market": "TWSE",
   "price": 60.1,
   "pct1": 3.09,
   "amount": 15.58
  },
  "6285": {
   "market": "TWSE",
   "price": 259.5,
   "pct1": 0.58,
   "amount": 12.49
  },
  "6414": {
   "market": "TWSE",
   "price": 383.5,
   "pct1": 2.13,
   "amount": 3.84
  },
  "6415": {
   "market": "TWSE",
   "price": 629.0,
   "pct1": 3.97,
   "amount": 8.64
  },
  "6416": {
   "market": "TWSE",
   "price": 83.3,
   "pct1": 1.46,
   "amount": 0.16
  },
  "6435": {
   "market": "TPEX",
   "price": 420.0,
   "pct1": 9.95,
   "amount": 4.3
  },
  "6442": {
   "market": "TWSE",
   "price": 1615.0,
   "pct1": -1.52,
   "amount": 15.01
  },
  "6443": {
   "market": "TWSE",
   "price": 34.6,
   "pct1": 0.44,
   "amount": 1.68
  },
  "6451": {
   "market": "TWSE",
   "price": 523.0,
   "pct1": -3.68,
   "amount": 11.85
  },
  "6485": {
   "market": "TPEX",
   "price": 81.8,
   "pct1": 0.62,
   "amount": 0.19
  },
  "6488": {
   "market": "TPEX",
   "price": 1330.0,
   "pct1": 5.98,
   "amount": 255.9
  },
  "6494": {
   "market": "TPEX",
   "price": 68.8,
   "pct1": 1.78,
   "amount": 0.25
  },
  "6510": {
   "market": "TPEX",
   "price": 3085.0,
   "pct1": -7.08,
   "amount": 8.83
  },
  "6515": {
   "market": "TWSE",
   "price": 9070.0,
   "pct1": -8.38,
   "amount": 18.37
  },
  "6531": {
   "market": "TWSE",
   "price": 971.0,
   "pct1": -1.62,
   "amount": 27.09
  },
  "6561": {
   "market": "TPEX",
   "price": 334.0,
   "pct1": -1.62,
   "amount": 0.3
  },
  "6569": {
   "market": "TPEX",
   "price": 107.0,
   "pct1": 1.42,
   "amount": 0.05
  },
  "6570": {
   "market": "TPEX",
   "price": 54.8,
   "pct1": 1.86,
   "amount": 0.08
  },
  "6573": {
   "market": "TWSE",
   "price": 26.8,
   "pct1": 6.77,
   "amount": 0.56
  },
  "6640": {
   "market": "TPEX",
   "price": 1135.0,
   "pct1": 0.89,
   "amount": 3.05
  },
  "6643": {
   "market": "TPEX",
   "price": 499.5,
   "pct1": -2.25,
   "amount": 1.96
  },
  "6667": {
   "market": "TPEX",
   "price": 270.0,
   "pct1": -0.37,
   "amount": 0.99
  },
  "6669": {
   "market": "TWSE",
   "price": 5050.0,
   "pct1": -4.08,
   "amount": 42.93
  },
  "6680": {
   "market": "TPEX",
   "price": 50.3,
   "pct1": -0.98,
   "amount": 0.0
  },
  "6689": {
   "market": "TWSE",
   "price": 65.0,
   "pct1": 1.72,
   "amount": 0.08
  },
  "6690": {
   "market": "TPEX",
   "price": 166.5,
   "pct1": -1.19,
   "amount": 0.12
  },
  "6691": {
   "market": "TWSE",
   "price": 764.0,
   "pct1": 0.26,
   "amount": 5.98
  },
  "6716": {
   "market": "TPEX",
   "price": 100.0,
   "pct1": 0.5,
   "amount": 0.31
  },
  "6739": {
   "market": "TPEX",
   "price": 1340.0,
   "pct1": 3.08,
   "amount": 11.25
  },
  "6753": {
   "market": "TWSE",
   "price": 157.5,
   "pct1": 2.27,
   "amount": 19.77
  },
  "6770": {
   "market": "TWSE",
   "price": 73.5,
   "pct1": 0.14,
   "amount": 82.67
  },
  "6788": {
   "market": "TPEX",
   "price": 437.5,
   "pct1": -1.69,
   "amount": 2.43
  },
  "6789": {
   "market": "TWSE",
   "price": 524.0,
   "pct1": -0.76,
   "amount": 6.45
  },
  "6805": {
   "market": "TWSE",
   "price": 1580.0,
   "pct1": -3.07,
   "amount": 19.13
  },
  "6811": {
   "market": "TPEX",
   "price": 224.0,
   "pct1": 0.9,
   "amount": 0.22
  },
  "6829": {
   "market": "TPEX",
   "price": 226.0,
   "pct1": -3.21,
   "amount": 1.98
  },
  "6857": {
   "market": "TPEX",
   "price": 94.9,
   "pct1": 0.42,
   "amount": 0.0
  },
  "6870": {
   "market": "TPEX",
   "price": 301.0,
   "pct1": -2.9,
   "amount": 0.13
  },
  "6907": {
   "market": "TPEX",
   "price": 187.5,
   "pct1": 9.97,
   "amount": 10.95
  },
  "7703": {
   "market": "TPEX",
   "price": 200.0,
   "pct1": 0.25,
   "amount": 0.28
  },
  "7717": {
   "market": "TPEX",
   "price": 456.0,
   "pct1": -1.41,
   "amount": 1.16
  },
  "7719": {
   "market": "TPEX",
   "price": 58.0,
   "pct1": -3.49,
   "amount": 1.04
  },
  "7750": {
   "market": "TWSE",
   "price": 2155.0,
   "pct1": -1.82,
   "amount": 1.48
  },
  "7769": {
   "market": "TWSE",
   "price": 6795.0,
   "pct1": -1.02,
   "amount": 14.71
  },
  "8016": {
   "market": "TWSE",
   "price": 335.5,
   "pct1": 0.45,
   "amount": 4.09
  },
  "8021": {
   "market": "TWSE",
   "price": 542.0,
   "pct1": -2.87,
   "amount": 2.2
  },
  "8028": {
   "market": "TWSE",
   "price": 336.0,
   "pct1": 0.45,
   "amount": 35.87
  },
  "8033": {
   "market": "TWSE",
   "price": 222.0,
   "pct1": 8.56,
   "amount": 18.52
  },
  "8038": {
   "market": "TPEX",
   "price": 40.7,
   "pct1": 1.37,
   "amount": 0.08
  },
  "8043": {
   "market": "TPEX",
   "price": 194.5,
   "pct1": -3.95,
   "amount": 18.4
  },
  "8044": {
   "market": "TPEX",
   "price": 28.55,
   "pct1": 1.42,
   "amount": 0.07
  },
  "8046": {
   "market": "TWSE",
   "price": 1085.0,
   "pct1": -8.44,
   "amount": 127.83
  },
  "8048": {
   "market": "TPEX",
   "price": 62.2,
   "pct1": -0.8,
   "amount": 0.09
  },
  "8050": {
   "market": "TPEX",
   "price": 56.9,
   "pct1": 1.79,
   "amount": 0.45
  },
  "8069": {
   "market": "TPEX",
   "price": 208.0,
   "pct1": -2.12,
   "amount": 11.98
  },
  "8081": {
   "market": "TWSE",
   "price": 322.0,
   "pct1": 0.78,
   "amount": 10.34
  },
  "8086": {
   "market": "TPEX",
   "price": 146.5,
   "pct1": 1.74,
   "amount": 3.88
  },
  "8099": {
   "market": "TPEX",
   "price": 59.8,
   "pct1": 1.01,
   "amount": 0.12
  },
  "8101": {
   "market": "TWSE",
   "price": 13.25,
   "pct1": -2.57,
   "amount": 0.0
  },
  "8114": {
   "market": "TWSE",
   "price": 205.0,
   "pct1": 0.99,
   "amount": 1.22
  },
  "8121": {
   "market": "TPEX",
   "price": 47.5,
   "pct1": -1.66,
   "amount": 1.11
  },
  "8131": {
   "market": "TWSE",
   "price": 82.2,
   "pct1": 9.89,
   "amount": 17.7
  },
  "8210": {
   "market": "TWSE",
   "price": 1290.0,
   "pct1": -1.15,
   "amount": 4.35
  },
  "8222": {
   "market": "TWSE",
   "price": 44.15,
   "pct1": -1.34,
   "amount": 4.42
  },
  "8234": {
   "market": "TPEX",
   "price": 71.5,
   "pct1": 0.7,
   "amount": 0.62
  },
  "8255": {
   "market": "TPEX",
   "price": 199.5,
   "pct1": 6.97,
   "amount": 8.87
  },
  "8261": {
   "market": "TWSE",
   "price": 352.0,
   "pct1": 10.0,
   "amount": 10.89
  },
  "8299": {
   "market": "TPEX",
   "price": 2300.0,
   "pct1": 0.22,
   "amount": 83.32
  },
  "8358": {
   "market": "TPEX",
   "price": 563.0,
   "pct1": -4.58,
   "amount": 44.01
  },
  "8374": {
   "market": "TWSE",
   "price": 92.7,
   "pct1": 0.0,
   "amount": 0.37
  },
  "8473": {
   "market": "TWSE",
   "price": 48.95,
   "pct1": -0.41,
   "amount": 0.18
  },
  "8996": {
   "market": "TWSE",
   "price": 1420.0,
   "pct1": 2.9,
   "amount": 8.11
  },
  "9802": {
   "market": "TWSE",
   "price": 74.6,
   "pct1": 0.27,
   "amount": 0.25
  },
  "9904": {
   "market": "TWSE",
   "price": 24.4,
   "pct1": -0.2,
   "amount": 3.24
  },
  "9910": {
   "market": "TWSE",
   "price": 68.5,
   "pct1": -0.15,
   "amount": 0.71
  },
  "9914": {
   "market": "TWSE",
   "price": 75.8,
   "pct1": -1.04,
   "amount": 0.51
  },
  "9919": {
   "market": "TWSE",
   "price": 14.0,
   "pct1": 0.0,
   "amount": 0.06
  },
  "9921": {
   "market": "TWSE",
   "price": 76.8,
   "pct1": 0.79,
   "amount": 0.66
  },
  "9941": {
   "market": "TWSE",
   "price": 82.9,
   "pct1": 0.61,
   "amount": 0.81
  }
 },
 "vixtwn": {
  "price": 36.61,
  "pct1": -3.2,
  "prev_close": null,
  "date": "2026-07-03",
  "time": "13:45"
 }
}