{
 "updated": "2026-06-17 12:11:34",
 "quotes": {
  "0050": {
   "market": "TWSE",
   "price": 105.3,
   "pct1": -0.57,
   "amount": 46.76
  },
  "1216": {
   "market": "TWSE",
   "price": 75.4,
   "pct1": -0.26,
   "amount": 4.7
  },
  "1301": {
   "market": "TWSE",
   "price": 47.6,
   "pct1": 1.82,
   "amount": 5.68
  },
  "1303": {
   "market": "TWSE",
   "price": 126.5,
   "pct1": 10.0,
   "amount": 110.29
  },
  "1409": {
   "market": "TWSE",
   "price": 27.8,
   "pct1": 3.35,
   "amount": 3.39
  },
  "1417": {
   "market": "TWSE",
   "price": 8.53,
   "pct1": -0.12,
   "amount": 0.01
  },
  "1466": {
   "market": "TWSE",
   "price": 14.0,
   "pct1": 0.0,
   "amount": 0.07
  },
  "1474": {
   "market": "TWSE",
   "price": 10.3,
   "pct1": 2.49,
   "amount": 0.01
  },
  "1476": {
   "market": "TWSE",
   "price": 322.5,
   "pct1": -6.11,
   "amount": 7.38
  },
  "1503": {
   "market": "TWSE",
   "price": 232.0,
   "pct1": 3.34,
   "amount": 21.26
  },
  "1504": {
   "market": "TWSE",
   "price": 68.5,
   "pct1": -4.6,
   "amount": 16.27
  },
  "1513": {
   "market": "TWSE",
   "price": 170.0,
   "pct1": 0.89,
   "amount": 10.92
  },
  "1514": {
   "market": "TWSE",
   "price": 120.0,
   "pct1": 0.0,
   "amount": 5.15
  },
  "1519": {
   "market": "TWSE",
   "price": 797.0,
   "pct1": 2.05,
   "amount": 23.38
  },
  "1536": {
   "market": "TWSE",
   "price": 48.95,
   "pct1": 0.1,
   "amount": 0.22
  },
  "1560": {
   "market": "TWSE",
   "price": 688.0,
   "pct1": 1.33,
   "amount": 4.1
  },
  "1590": {
   "market": "TWSE",
   "price": 1310.0,
   "pct1": 1.16,
   "amount": 2.88
  },
  "1597": {
   "market": "TWSE",
   "price": 148.5,
   "pct1": -1.0,
   "amount": 0.81
  },
  "1603": {
   "market": "TWSE",
   "price": 31.7,
   "pct1": -0.16,
   "amount": 0.04
  },
  "1604": {
   "market": "TWSE",
   "price": 23.15,
   "pct1": -0.22,
   "amount": 0.07
  },
  "1605": {
   "market": "TWSE",
   "price": 38.45,
   "pct1": -1.79,
   "amount": 9.5
  },
  "1609": {
   "market": "TWSE",
   "price": 38.1,
   "pct1": 0.93,
   "amount": 1.05
  },
  "1611": {
   "market": "TWSE",
   "price": 13.35,
   "pct1": 2.3,
   "amount": 0.07
  },
  "1612": {
   "market": "TWSE",
   "price": 37.95,
   "pct1": 0.26,
   "amount": 0.2
  },
  "1615": {
   "market": "TWSE",
   "price": 44.8,
   "pct1": 0.11,
   "amount": 0.03
  },
  "1626": {
   "market": "TWSE",
   "price": 10.0,
   "pct1": 0.0,
   "amount": 0.0
  },
  "1784": {
   "market": "TPEX",
   "price": 67.0,
   "pct1": 1.67,
   "amount": 0.07
  },
  "1815": {
   "market": "TPEX",
   "price": 95.1,
   "pct1": 0.32,
   "amount": 6.78
  },
  "2002": {
   "market": "TWSE",
   "price": 18.65,
   "pct1": 0.0,
   "amount": 5.31
  },
  "2049": {
   "market": "TWSE",
   "price": 321.0,
   "pct1": -1.08,
   "amount": 4.16
  },
  "2059": {
   "market": "TWSE",
   "price": 6550.0,
   "pct1": -1.5,
   "amount": 10.97
  },
  "2207": {
   "market": "TWSE",
   "price": 460.5,
   "pct1": -1.71,
   "amount": 1.82
  },
  "2208": {
   "market": "TWSE",
   "price": 17.85,
   "pct1": 0.85,
   "amount": 0.19
  },
  "2231": {
   "market": "TWSE",
   "price": 93.4,
   "pct1": -1.68,
   "amount": 0.13
  },
  "2233": {
   "market": "TWSE",
   "price": 304.5,
   "pct1": 0.0,
   "amount": 1.76
  },
  "2236": {
   "market": "TWSE",
   "price": 134.5,
   "pct1": 0.37,
   "amount": 0.09
  },
  "2301": {
   "market": "TWSE",
   "price": 209.5,
   "pct1": 0.72,
   "amount": 16.87
  },
  "2303": {
   "market": "TWSE",
   "price": 137.5,
   "pct1": -2.48,
   "amount": 141.22
  },
  "2308": {
   "market": "TWSE",
   "price": 2160.0,
   "pct1": -3.14,
   "amount": 154.32
  },
  "2313": {
   "market": "TWSE",
   "price": 263.0,
   "pct1": 5.62,
   "amount": 150.8
  },
  "2317": {
   "market": "TWSE",
   "price": 269.0,
   "pct1": 0.0,
   "amount": 64.14
  },
  "2324": {
   "market": "TWSE",
   "price": 37.2,
   "pct1": -0.53,
   "amount": 10.88
  },
  "2327": {
   "market": "TWSE",
   "price": 987.0,
   "pct1": 3.89,
   "amount": 362.97
  },
  "2329": {
   "market": "TWSE",
   "price": 54.2,
   "pct1": 0.37,
   "amount": 2.06
  },
  "2330": {
   "market": "TWSE",
   "price": 2360.0,
   "pct1": -1.67,
   "amount": 316.13
  },
  "2337": {
   "market": "TWSE",
   "price": 161.0,
   "pct1": -3.3,
   "amount": 133.77
  },
  "2344": {
   "market": "TWSE",
   "price": 191.5,
   "pct1": -2.79,
   "amount": 301.96
  },
  "2345": {
   "market": "TWSE",
   "price": 2510.0,
   "pct1": -0.4,
   "amount": 44.04
  },
  "2353": {
   "market": "TWSE",
   "price": 34.5,
   "pct1": -11.31,
   "amount": 29.22
  },
  "2355": {
   "market": "TWSE",
   "price": 57.3,
   "pct1": 0.35,
   "amount": 4.25
  },
  "2356": {
   "market": "TWSE",
   "price": 66.6,
   "pct1": 0.0,
   "amount": 7.63
  },
  "2357": {
   "market": "TWSE",
   "price": 799.0,
   "pct1": 1.01,
   "amount": 13.96
  },
  "2359": {
   "market": "TWSE",
   "price": 131.0,
   "pct1": -1.5,
   "amount": 1.37
  },
  "2360": {
   "market": "TWSE",
   "price": 2225.0,
   "pct1": -4.3,
   "amount": 42.64
  },
  "2367": {
   "market": "TWSE",
   "price": 61.0,
   "pct1": 0.49,
   "amount": 11.94
  },
  "2368": {
   "market": "TWSE",
   "price": 1360.0,
   "pct1": 1.12,
   "amount": 24.62
  },
  "2371": {
   "market": "TWSE",
   "price": 27.9,
   "pct1": -0.53,
   "amount": 1.63
  },
  "2375": {
   "market": "TWSE",
   "price": 199.5,
   "pct1": 9.92,
   "amount": 52.82
  },
  "2376": {
   "market": "TWSE",
   "price": 347.5,
   "pct1": -0.14,
   "amount": 10.56
  },
  "2377": {
   "market": "TWSE",
   "price": 135.0,
   "pct1": -1.1,
   "amount": 8.33
  },
  "2379": {
   "market": "TWSE",
   "price": 673.0,
   "pct1": -0.74,
   "amount": 11.81
  },
  "2382": {
   "market": "TWSE",
   "price": 367.0,
   "pct1": 1.24,
   "amount": 46.92
  },
  "2383": {
   "market": "TWSE",
   "price": 5215.0,
   "pct1": 1.86,
   "amount": 90.53
  },
  "2395": {
   "market": "TWSE",
   "price": 485.5,
   "pct1": 1.15,
   "amount": 3.65
  },
  "2397": {
   "market": "TWSE",
   "price": 61.3,
   "pct1": 0.66,
   "amount": 0.08
  },
  "2401": {
   "market": "TWSE",
   "price": 31.4,
   "pct1": 2.11,
   "amount": 3.82
  },
  "2404": {
   "market": "TWSE",
   "price": 1275.0,
   "pct1": 2.41,
   "amount": 38.47
  },
  "2408": {
   "market": "TWSE",
   "price": 425.0,
   "pct1": 0.0,
   "amount": 294.1
  },
  "2409": {
   "market": "TWSE",
   "price": 26.25,
   "pct1": 9.83,
   "amount": 142.97
  },
  "2412": {
   "market": "TWSE",
   "price": 145.5,
   "pct1": -0.68,
   "amount": 7.82
  },
  "2413": {
   "market": "TWSE",
   "price": 57.1,
   "pct1": -4.03,
   "amount": 1.46
  },
  "2419": {
   "market": "TWSE",
   "price": 29.65,
   "pct1": 2.42,
   "amount": 0.31
  },
  "2421": {
   "market": "TWSE",
   "price": 144.5,
   "pct1": 1.4,
   "amount": 1.8
  },
  "2428": {
   "market": "TWSE",
   "price": 294.5,
   "pct1": 5.18,
   "amount": 4.1
  },
  "2429": {
   "market": "TWSE",
   "price": 38.65,
   "pct1": 0.52,
   "amount": 0.11
  },
  "2436": {
   "market": "TWSE",
   "price": 68.0,
   "pct1": 1.04,
   "amount": 0.65
  },
  "2449": {
   "market": "TWSE",
   "price": 281.0,
   "pct1": 1.08,
   "amount": 14.91
  },
  "2451": {
   "market": "TWSE",
   "price": 305.5,
   "pct1": -2.24,
   "amount": 10.59
  },
  "2454": {
   "market": "TWSE",
   "price": 4420.0,
   "pct1": -3.07,
   "amount": 243.23
  },
  "2455": {
   "market": "TWSE",
   "price": 424.5,
   "pct1": 4.69,
   "amount": 83.63
  },
  "2464": {
   "market": "TWSE",
   "price": 169.5,
   "pct1": -5.57,
   "amount": 46.85
  },
  "2467": {
   "market": "TWSE",
   "price": 589.0,
   "pct1": 4.43,
   "amount": 5.49
  },
  "2471": {
   "market": "TWSE",
   "price": 54.1,
   "pct1": 1.5,
   "amount": 0.06
  },
  "2472": {
   "market": "TWSE",
   "price": 358.5,
   "pct1": 3.17,
   "amount": 39.09
  },
  "2474": {
   "market": "TWSE",
   "price": 204.5,
   "pct1": -0.49,
   "amount": 5.27
  },
  "2478": {
   "market": "TWSE",
   "price": 227.5,
   "pct1": 9.9,
   "amount": 41.22
  },
  "2480": {
   "market": "TWSE",
   "price": 145.0,
   "pct1": -1.36,
   "amount": 0.65
  },
  "2489": {
   "market": "TWSE",
   "price": 48.45,
   "pct1": 5.56,
   "amount": 22.8
  },
  "2492": {
   "market": "TWSE",
   "price": 541.0,
   "pct1": 9.51,
   "amount": 17.0
  },
  "2603": {
   "market": "TWSE",
   "price": 194.0,
   "pct1": -12.02,
   "amount": 83.83
  },
  "2609": {
   "market": "TWSE",
   "price": 51.5,
   "pct1": 0.98,
   "amount": 11.0
  },
  "2610": {
   "market": "TWSE",
   "price": 22.0,
   "pct1": 3.77,
   "amount": 28.23
  },
  "2615": {
   "market": "TWSE",
   "price": 81.2,
   "pct1": -0.37,
   "amount": 3.1
  },
  "2618": {
   "market": "TWSE",
   "price": 42.65,
   "pct1": 7.3,
   "amount": 66.55
  },
  "2630": {
   "market": "TWSE",
   "price": 39.35,
   "pct1": 1.68,
   "amount": 0.28
  },
  "2634": {
   "market": "TWSE",
   "price": 47.1,
   "pct1": 0.75,
   "amount": 0.98
  },
  "2637": {
   "market": "TWSE",
   "price": 77.5,
   "pct1": -1.15,
   "amount": 2.55
  },
  "2644": {
   "market": "TPEX",
   "price": 81.3,
   "pct1": -0.25,
   "amount": 0.01
  },
  "2645": {
   "market": "TWSE",
   "price": 168.5,
   "pct1": 0.3,
   "amount": 0.74
  },
  "2706": {
   "market": "TWSE",
   "price": 12.35,
   "pct1": -0.4,
   "amount": 0.0
  },
  "2723": {
   "market": "TWSE",
   "price": 66.7,
   "pct1": -1.62,
   "amount": 0.09
  },
  "2727": {
   "market": "TWSE",
   "price": 244.0,
   "pct1": 0.0,
   "amount": 0.3
  },
  "2731": {
   "market": "TWSE",
   "price": 153.0,
   "pct1": 0.0,
   "amount": 1.12
  },
  "2881": {
   "market": "TWSE",
   "price": 134.5,
   "pct1": 1.89,
   "amount": 34.69
  },
  "2882": {
   "market": "TWSE",
   "price": 113.0,
   "pct1": 3.2,
   "amount": 38.41
  },
  "2884": {
   "market": "TWSE",
   "price": 35.5,
   "pct1": 0.85,
   "amount": 14.14
  },
  "2886": {
   "market": "TWSE",
   "price": 45.0,
   "pct1": 1.12,
   "amount": 8.33
  },
  "2891": {
   "market": "TWSE",
   "price": 70.9,
   "pct1": 0.14,
   "amount": 14.94
  },
  "2912": {
   "market": "TWSE",
   "price": 227.5,
   "pct1": -0.22,
   "amount": 3.24
  },
  "2929": {
   "market": "TWSE",
   "price": 5.78,
   "pct1": 0.0,
   "amount": 0.0
  },
  "2949": {
   "market": "TPEX",
   "price": 65.6,
   "pct1": 0.61,
   "amount": 0.0
  },
  "3005": {
   "market": "TWSE",
   "price": 103.0,
   "pct1": 1.48,
   "amount": 1.38
  },
  "3006": {
   "market": "TWSE",
   "price": 225.5,
   "pct1": 0.45,
   "amount": 10.67
  },
  "3008": {
   "market": "TWSE",
   "price": 5100.0,
   "pct1": 4.94,
   "amount": 243.3
  },
  "3013": {
   "market": "TWSE",
   "price": 111.0,
   "pct1": 0.45,
   "amount": 1.04
  },
  "3014": {
   "market": "TWSE",
   "price": 150.0,
   "pct1": 0.0,
   "amount": 2.15
  },
  "3016": {
   "market": "TWSE",
   "price": 124.5,
   "pct1": 4.18,
   "amount": 14.42
  },
  "3017": {
   "market": "TWSE",
   "price": 2355.0,
   "pct1": -0.63,
   "amount": 65.13
  },
  "3022": {
   "market": "TWSE",
   "price": 83.8,
   "pct1": 1.45,
   "amount": 0.7
  },
  "3024": {
   "market": "TWSE",
   "price": 12.4,
   "pct1": 2.06,
   "amount": 0.14
  },
  "3026": {
   "market": "TWSE",
   "price": 896.0,
   "pct1": 9.94,
   "amount": 138.61
  },
  "3027": {
   "market": "TWSE",
   "price": 20.65,
   "pct1": -0.24,
   "amount": 0.08
  },
  "3029": {
   "market": "TWSE",
   "price": 102.0,
   "pct1": 0.0,
   "amount": 0.49
  },
  "3030": {
   "market": "TWSE",
   "price": 333.0,
   "pct1": 0.76,
   "amount": 2.49
  },
  "3032": {
   "market": "TWSE",
   "price": 84.8,
   "pct1": 0.95,
   "amount": 0.32
  },
  "3034": {
   "market": "TWSE",
   "price": 503.0,
   "pct1": 0.6,
   "amount": 13.57
  },
  "3035": {
   "market": "TWSE",
   "price": 199.0,
   "pct1": -1.0,
   "amount": 7.22
  },
  "3037": {
   "market": "TWSE",
   "price": 985.0,
   "pct1": 0.41,
   "amount": 131.91
  },
  "3044": {
   "market": "TWSE",
   "price": 568.0,
   "pct1": 4.03,
   "amount": 23.24
  },
  "3081": {
   "market": "TPEX",
   "price": 2270.0,
   "pct1": -0.44,
   "amount": 28.47
  },
  "3088": {
   "market": "TPEX",
   "price": 141.0,
   "pct1": 3.3,
   "amount": 1.3
  },
  "3105": {
   "market": "TPEX",
   "price": 506.0,
   "pct1": 2.64,
   "amount": 69.13
  },
  "3131": {
   "market": "TPEX",
   "price": 3245.0,
   "pct1": -2.11,
   "amount": 7.73
  },
  "3163": {
   "market": "TPEX",
   "price": 897.0,
   "pct1": 2.4,
   "amount": 29.64
  },
  "3167": {
   "market": "TWSE",
   "price": 805.0,
   "pct1": 0.62,
   "amount": 2.58
  },
  "3189": {
   "market": "TWSE",
   "price": 706.0,
   "pct1": 9.97,
   "amount": 207.3
  },
  "3231": {
   "market": "TWSE",
   "price": 162.0,
   "pct1": 2.53,
   "amount": 61.29
  },
  "3260": {
   "market": "TPEX",
   "price": 414.5,
   "pct1": -0.6,
   "amount": 24.35
  },
  "3324": {
   "market": "TPEX",
   "price": 1040.0,
   "pct1": -0.95,
   "amount": 10.37
  },
  "3357": {
   "market": "TPEX",
   "price": 309.5,
   "pct1": 2.82,
   "amount": 18.86
  },
  "3363": {
   "market": "TPEX",
   "price": 687.0,
   "pct1": -2.83,
   "amount": 13.83
  },
  "3376": {
   "market": "TWSE",
   "price": 198.0,
   "pct1": -1.0,
   "amount": 5.14
  },
  "3402": {
   "market": "TPEX",
   "price": 139.0,
   "pct1": -0.71,
   "amount": 0.4
  },
  "3413": {
   "market": "TWSE",
   "price": 319.5,
   "pct1": -2.14,
   "amount": 4.7
  },
  "3416": {
   "market": "TWSE",
   "price": 173.5,
   "pct1": 0.0,
   "amount": 0.15
  },
  "3443": {
   "market": "TWSE",
   "price": 5065.0,
   "pct1": 2.95,
   "amount": 107.99
  },
  "3450": {
   "market": "TWSE",
   "price": 514.0,
   "pct1": 2.9,
   "amount": 32.19
  },
  "3479": {
   "market": "TPEX",
   "price": 133.0,
   "pct1": 5.56,
   "amount": 1.82
  },
  "3481": {
   "market": "TWSE",
   "price": 57.9,
   "pct1": 8.63,
   "amount": 83.55
  },
  "3483": {
   "market": "TPEX",
   "price": 91.4,
   "pct1": 0.88,
   "amount": 0.21
  },
  "3491": {
   "market": "TPEX",
   "price": 1565.0,
   "pct1": -0.32,
   "amount": 18.79
  },
  "3515": {
   "market": "TWSE",
   "price": 243.5,
   "pct1": 0.0,
   "amount": 0.61
  },
  "3530": {
   "market": "TWSE",
   "price": 71.5,
   "pct1": 10.0,
   "amount": 0.98
  },
  "3551": {
   "market": "TPEX",
   "price": 199.5,
   "pct1": -0.25,
   "amount": 0.41
  },
  "3556": {
   "market": "TPEX",
   "price": 74.2,
   "pct1": 0.27,
   "amount": 0.33
  },
  "3558": {
   "market": "TPEX",
   "price": 135.0,
   "pct1": 0.0,
   "amount": 0.15
  },
  "3564": {
   "market": "TPEX",
   "price": 47.65,
   "pct1": 0.21,
   "amount": 0.07
  },
  "3583": {
   "market": "TWSE",
   "price": 827.0,
   "pct1": 1.22,
   "amount": 3.39
  },
  "3594": {
   "market": "TPEX",
   "price": 46.95,
   "pct1": -0.74,
   "amount": 0.04
  },
  "3596": {
   "market": "TWSE",
   "price": 192.5,
   "pct1": 3.22,
   "amount": 4.53
  },
  "3653": {
   "market": "TWSE",
   "price": 3950.0,
   "pct1": 4.36,
   "amount": 43.08
  },
  "3661": {
   "market": "TWSE",
   "price": 4265.0,
   "pct1": -1.16,
   "amount": 43.51
  },
  "3665": {
   "market": "TWSE",
   "price": 2070.0,
   "pct1": -2.36,
   "amount": 42.73
  },
  "3673": {
   "market": "TWSE",
   "price": 86.6,
   "pct1": 9.9,
   "amount": 25.97
  },
  "3680": {
   "market": "TPEX",
   "price": 511.0,
   "pct1": 2.2,
   "amount": 5.0
  },
  "3686": {
   "market": "TWSE",
   "price": 17.35,
   "pct1": 1.46,
   "amount": 0.03
  },
  "3693": {
   "market": "TPEX",
   "price": 496.5,
   "pct1": -0.5,
   "amount": 1.23
  },
  "3704": {
   "market": "TWSE",
   "price": 49.5,
   "pct1": 6.0,
   "amount": 4.49
  },
  "3706": {
   "market": "TWSE",
   "price": 85.6,
   "pct1": 1.54,
   "amount": 12.04
  },
  "3707": {
   "market": "TPEX",
   "price": 81.5,
   "pct1": 2.26,
   "amount": 7.56
  },
  "3711": {
   "market": "TWSE",
   "price": 588.0,
   "pct1": -0.68,
   "amount": 47.36
  },
  "4540": {
   "market": "TWSE",
   "price": 59.4,
   "pct1": -0.34,
   "amount": 0.86
  },
  "4541": {
   "market": "TPEX",
   "price": 50.4,
   "pct1": 5.0,
   "amount": 1.2
  },
  "4576": {
   "market": "TWSE",
   "price": 198.5,
   "pct1": -3.87,
   "amount": 1.69
  },
  "4585": {
   "market": "TWSE",
   "price": 308.0,
   "pct1": 0.49,
   "amount": 0.2
  },
  "4749": {
   "market": "TPEX",
   "price": 941.0,
   "pct1": 0.43,
   "amount": 4.19
  },
  "4763": {
   "market": "TWSE",
   "price": 44.35,
   "pct1": -1.0,
   "amount": 1.11
  },
  "4772": {
   "market": "TPEX",
   "price": 276.5,
   "pct1": 0.55,
   "amount": 0.72
  },
  "4906": {
   "market": "TWSE",
   "price": 43.55,
   "pct1": 1.52,
   "amount": 2.01
  },
  "4916": {
   "market": "TWSE",
   "price": 99.3,
   "pct1": 0.3,
   "amount": 4.82
  },
  "4938": {
   "market": "TWSE",
   "price": 81.7,
   "pct1": -1.57,
   "amount": 10.55
  },
  "4943": {
   "market": "TWSE",
   "price": 9.0,
   "pct1": -0.77,
   "amount": 0.0
  },
  "4953": {
   "market": "TPEX",
   "price": 133.0,
   "pct1": -1.48,
   "amount": 0.56
  },
  "4958": {
   "market": "TWSE",
   "price": 627.0,
   "pct1": 0.48,
   "amount": 180.56
  },
  "4961": {
   "market": "TWSE",
   "price": 170.0,
   "pct1": 1.19,
   "amount": 0.56
  },
  "4966": {
   "market": "TPEX",
   "price": 661.0,
   "pct1": 0.15,
   "amount": 4.33
  },
  "4967": {
   "market": "TWSE",
   "price": 273.0,
   "pct1": -0.73,
   "amount": 6.32
  },
  "4971": {
   "market": "TPEX",
   "price": 527.0,
   "pct1": -3.66,
   "amount": 3.71
  },
  "4977": {
   "market": "TWSE",
   "price": 179.0,
   "pct1": -0.83,
   "amount": 1.88
  },
  "4979": {
   "market": "TPEX",
   "price": 547.0,
   "pct1": -3.7,
   "amount": 29.58
  },
  "5222": {
   "market": "TWSE",
   "price": 113.5,
   "pct1": 0.89,
   "amount": 0.19
  },
  "5258": {
   "market": "TWSE",
   "price": 49.9,
   "pct1": 1.32,
   "amount": 0.12
  },
  "5269": {
   "market": "TWSE",
   "price": 1425.0,
   "pct1": 3.26,
   "amount": 8.3
  },
  "5274": {
   "market": "TPEX",
   "price": 18250.0,
   "pct1": 0.52,
   "amount": 11.22
  },
  "5285": {
   "market": "TWSE",
   "price": 88.4,
   "pct1": 0.68,
   "amount": 0.71
  },
  "5289": {
   "market": "TPEX",
   "price": 1845.0,
   "pct1": -5.63,
   "amount": 44.6
  },
  "5328": {
   "market": "TPEX",
   "price": 49.25,
   "pct1": -3.81,
   "amount": 22.25
  },
  "5340": {
   "market": "TPEX",
   "price": 88.0,
   "pct1": -0.56,
   "amount": 0.79
  },
  "5347": {
   "market": "TPEX",
   "price": 167.0,
   "pct1": -2.62,
   "amount": 10.13
  },
  "5371": {
   "market": "TPEX",
   "price": 68.6,
   "pct1": 1.18,
   "amount": 0.98
  },
  "5388": {
   "market": "TWSE",
   "price": 84.3,
   "pct1": 0.12,
   "amount": 1.06
  },
  "5439": {
   "market": "TPEX",
   "price": 319.0,
   "pct1": -1.09,
   "amount": 4.93
  },
  "5443": {
   "market": "TPEX",
   "price": 104.5,
   "pct1": 0.48,
   "amount": 0.58
  },
  "5471": {
   "market": "TWSE",
   "price": 59.2,
   "pct1": 2.96,
   "amount": 3.82
  },
  "5474": {
   "market": "TPEX",
   "price": 179.5,
   "pct1": 2.87,
   "amount": 0.49
  },
  "5536": {
   "market": "TPEX",
   "price": 1185.0,
   "pct1": 0.85,
   "amount": 3.75
  },
  "5706": {
   "market": "TWSE",
   "price": 53.4,
   "pct1": 0.75,
   "amount": 0.11
  },
  "5871": {
   "market": "TWSE",
   "price": 115.0,
   "pct1": -1.29,
   "amount": 3.52
  },
  "5903": {
   "market": "TPEX",
   "price": 188.5,
   "pct1": 0.0,
   "amount": 0.03
  },
  "6112": {
   "market": "TWSE",
   "price": 45.6,
   "pct1": 0.22,
   "amount": 0.18
  },
  "6116": {
   "market": "TWSE",
   "price": 18.25,
   "pct1": 9.94,
   "amount": 4.92
  },
  "6117": {
   "market": "TWSE",
   "price": 75.4,
   "pct1": -0.13,
   "amount": 0.1
  },
  "6121": {
   "market": "TPEX",
   "price": 408.0,
   "pct1": -3.09,
   "amount": 2.18
  },
  "6125": {
   "market": "TPEX",
   "price": 60.8,
   "pct1": 1.67,
   "amount": 0.47
  },
  "6128": {
   "market": "TWSE",
   "price": 21.05,
   "pct1": 0.48,
   "amount": 0.02
  },
  "6138": {
   "market": "TPEX",
   "price": 324.0,
   "pct1": 3.68,
   "amount": 2.03
  },
  "6139": {
   "market": "TWSE",
   "price": 808.0,
   "pct1": -0.49,
   "amount": 20.16
  },
  "6146": {
   "market": "TPEX",
   "price": 193.5,
   "pct1": -0.26,
   "amount": 0.24
  },
  "6147": {
   "market": "TPEX",
   "price": 230.0,
   "pct1": 1.1,
   "amount": 41.4
  },
  "6155": {
   "market": "TWSE",
   "price": 88.8,
   "pct1": 1.37,
   "amount": 13.25
  },
  "6163": {
   "market": "TPEX",
   "price": 50.6,
   "pct1": -1.36,
   "amount": 0.38
  },
  "6166": {
   "market": "TWSE",
   "price": 140.5,
   "pct1": 1.81,
   "amount": 1.32
  },
  "6168": {
   "market": "TWSE",
   "price": 27.9,
   "pct1": -0.89,
   "amount": 0.91
  },
  "6173": {
   "market": "TPEX",
   "price": 302.0,
   "pct1": 5.23,
   "amount": 4.08
  },
  "6182": {
   "market": "TPEX",
   "price": 116.5,
   "pct1": 8.88,
   "amount": 157.24
  },
  "6187": {
   "market": "TPEX",
   "price": 1140.0,
   "pct1": 0.0,
   "amount": 3.96
  },
  "6188": {
   "market": "TPEX",
   "price": 79.8,
   "pct1": 0.88,
   "amount": 0.46
  },
  "6196": {
   "market": "TWSE",
   "price": 535.0,
   "pct1": -1.11,
   "amount": 6.29
  },
  "6202": {
   "market": "TWSE",
   "price": 65.0,
   "pct1": 4.84,
   "amount": 6.89
  },
  "6206": {
   "market": "TWSE",
   "price": 130.5,
   "pct1": 1.16,
   "amount": 0.43
  },
  "6213": {
   "market": "TWSE",
   "price": 270.0,
   "pct1": 4.65,
   "amount": 19.99
  },
  "6214": {
   "market": "TWSE",
   "price": 141.5,
   "pct1": 0.35,
   "amount": 0.71
  },
  "6223": {
   "market": "TPEX",
   "price": 6400.0,
   "pct1": -0.7,
   "amount": 23.93
  },
  "6239": {
   "market": "TWSE",
   "price": 345.5,
   "pct1": -0.29,
   "amount": 110.21
  },
  "6244": {
   "market": "TPEX",
   "price": 28.8,
   "pct1": -1.03,
   "amount": 1.77
  },
  "6245": {
   "market": "TPEX",
   "price": 82.3,
   "pct1": 1.23,
   "amount": 0.28
  },
  "6263": {
   "market": "TPEX",
   "price": 164.0,
   "pct1": 2.5,
   "amount": 0.69
  },
  "6271": {
   "market": "TWSE",
   "price": 227.0,
   "pct1": 1.11,
   "amount": 7.22
  },
  "6274": {
   "market": "TPEX",
   "price": 1665.0,
   "pct1": 3.42,
   "amount": 72.49
  },
  "6278": {
   "market": "TWSE",
   "price": 205.0,
   "pct1": -2.15,
   "amount": 7.78
  },
  "6282": {
   "market": "TWSE",
   "price": 57.4,
   "pct1": -0.52,
   "amount": 7.29
  },
  "6285": {
   "market": "TWSE",
   "price": 266.0,
   "pct1": 0.19,
   "amount": 41.5
  },
  "6414": {
   "market": "TWSE",
   "price": 367.5,
   "pct1": 0.14,
   "amount": 3.65
  },
  "6415": {
   "market": "TWSE",
   "price": 579.0,
   "pct1": -1.53,
   "amount": 45.39
  },
  "6416": {
   "market": "TWSE",
   "price": 83.4,
   "pct1": -0.6,
   "amount": 0.03
  },
  "6442": {
   "market": "TWSE",
   "price": 1840.0,
   "pct1": -1.87,
   "amount": 7.31
  },
  "6443": {
   "market": "TWSE",
   "price": 38.9,
   "pct1": -0.38,
   "amount": 2.6
  },
  "6451": {
   "market": "TWSE",
   "price": 540.0,
   "pct1": -1.64,
   "amount": 10.83
  },
  "6485": {
   "market": "TPEX",
   "price": 86.9,
   "pct1": -1.25,
   "amount": 0.28
  },
  "6488": {
   "market": "TPEX",
   "price": 1130.0,
   "pct1": 8.13,
   "amount": 150.02
  },
  "6510": {
   "market": "TPEX",
   "price": 3565.0,
   "pct1": 1.86,
   "amount": 7.08
  },
  "6515": {
   "market": "TWSE",
   "price": 9550.0,
   "pct1": -3.97,
   "amount": 21.01
  },
  "6531": {
   "market": "TWSE",
   "price": 934.0,
   "pct1": 1.08,
   "amount": 18.03
  },
  "6561": {
   "market": "TPEX",
   "price": 338.5,
   "pct1": -0.15,
   "amount": 0.09
  },
  "6569": {
   "market": "TPEX",
   "price": 114.0,
   "pct1": 0.0,
   "amount": 0.05
  },
  "6570": {
   "market": "TPEX",
   "price": 53.1,
   "pct1": -1.67,
   "amount": 0.08
  },
  "6573": {
   "market": "TWSE",
   "price": 14.9,
   "pct1": 0.68,
   "amount": 0.03
  },
  "6640": {
   "market": "TPEX",
   "price": 1085.0,
   "pct1": -2.69,
   "amount": 0.93
  },
  "6643": {
   "market": "TPEX",
   "price": 480.0,
   "pct1": -0.72,
   "amount": 1.17
  },
  "6667": {
   "market": "TPEX",
   "price": 276.5,
   "pct1": 0.18,
   "amount": 0.71
  },
  "6669": {
   "market": "TWSE",
   "price": 5005.0,
   "pct1": 2.56,
   "amount": 38.29
  },
  "6680": {
   "market": "TPEX",
   "price": 53.8,
   "pct1": -0.19,
   "amount": 0.0
  },
  "6689": {
   "market": "TWSE",
   "price": 68.1,
   "pct1": 0.44,
   "amount": 0.09
  },
  "6690": {
   "market": "TPEX",
   "price": 176.5,
   "pct1": -0.56,
   "amount": 0.12
  },
  "6691": {
   "market": "TWSE",
   "price": 713.0,
   "pct1": 0.42,
   "amount": 4.5
  },
  "6739": {
   "market": "TPEX",
   "price": 1110.0,
   "pct1": -2.63,
   "amount": 1.04
  },
  "6753": {
   "market": "TWSE",
   "price": 119.5,
   "pct1": 0.42,
   "amount": 0.37
  },
  "6770": {
   "market": "TWSE",
   "price": 70.5,
   "pct1": -0.7,
   "amount": 79.74
  },
  "6788": {
   "market": "TPEX",
   "price": 434.0,
   "pct1": 1.64,
   "amount": 1.99
  },
  "6789": {
   "market": "TWSE",
   "price": 493.0,
   "pct1": 1.02,
   "amount": 4.23
  },
  "6805": {
   "market": "TWSE",
   "price": 1700.0,
   "pct1": -1.45,
   "amount": 8.8
  },
  "6811": {
   "market": "TPEX",
   "price": 231.0,
   "pct1": 0.43,
   "amount": 0.3
  },
  "6829": {
   "market": "TPEX",
   "price": 200.0,
   "pct1": -4.76,
   "amount": 1.17
  },
  "6857": {
   "market": "TPEX",
   "price": 94.0,
   "pct1": -0.53,
   "amount": 0.0
  },
  "6870": {
   "market": "TPEX",
   "price": 278.5,
   "pct1": -0.54,
   "amount": 0.14
  },
  "7703": {
   "market": "TPEX",
   "price": 204.0,
   "pct1": -0.97,
   "amount": 0.13
  },
  "7717": {
   "market": "TPEX",
   "price": 545.0,
   "pct1": -1.09,
   "amount": 1.08
  },
  "7719": {
   "market": "TPEX",
   "price": 40.1,
   "pct1": 1.91,
   "amount": 0.03
  },
  "7750": {
   "market": "TWSE",
   "price": 2220.0,
   "pct1": -2.42,
   "amount": 1.97
  },
  "7769": {
   "market": "TWSE",
   "price": 7215.0,
   "pct1": -1.97,
   "amount": 18.39
  },
  "8016": {
   "market": "TWSE",
   "price": 288.0,
   "pct1": 3.41,
   "amount": 4.48
  },
  "8021": {
   "market": "TWSE",
   "price": 544.0,
   "pct1": 5.02,
   "amount": 7.93
  },
  "8028": {
   "market": "TWSE",
   "price": 306.0,
   "pct1": -2.55,
   "amount": 13.52
  },
  "8033": {
   "market": "TWSE",
   "price": 127.5,
   "pct1": 2.0,
   "amount": 1.64
  },
  "8038": {
   "market": "TPEX",
   "price": 40.15,
   "pct1": -1.23,
   "amount": 0.06
  },
  "8043": {
   "market": "TPEX",
   "price": 220.0,
   "pct1": 4.27,
   "amount": 66.89
  },
  "8044": {
   "market": "TPEX",
   "price": 28.45,
   "pct1": -0.7,
   "amount": 0.12
  },
  "8046": {
   "market": "TWSE",
   "price": 879.0,
   "pct1": -2.55,
   "amount": 114.95
  },
  "8048": {
   "market": "TPEX",
   "price": 66.5,
   "pct1": 1.68,
   "amount": 0.29
  },
  "8050": {
   "market": "TPEX",
   "price": 54.8,
   "pct1": -0.72,
   "amount": 0.41
  },
  "8069": {
   "market": "TPEX",
   "price": 196.5,
   "pct1": 1.03,
   "amount": 6.31
  },
  "8081": {
   "market": "TWSE",
   "price": 291.5,
   "pct1": 3.19,
   "amount": 2.86
  },
  "8086": {
   "market": "TPEX",
   "price": 159.0,
   "pct1": -0.62,
   "amount": 4.19
  },
  "8099": {
   "market": "TPEX",
   "price": 59.9,
   "pct1": 0.5,
   "amount": 0.02
  },
  "8101": {
   "market": "TWSE",
   "price": 15.0,
   "pct1": 0.0,
   "amount": 0.0
  },
  "8114": {
   "market": "TWSE",
   "price": 207.0,
   "pct1": -0.48,
   "amount": 1.37
  },
  "8131": {
   "market": "TWSE",
   "price": 74.5,
   "pct1": -1.97,
   "amount": 3.57
  },
  "8210": {
   "market": "TWSE",
   "price": 1355.0,
   "pct1": 0.37,
   "amount": 5.02
  },
  "8222": {
   "market": "TWSE",
   "price": 35.5,
   "pct1": 2.6,
   "amount": 0.07
  },
  "8234": {
   "market": "TPEX",
   "price": 62.7,
   "pct1": -0.79,
   "amount": 0.14
  },
  "8255": {
   "market": "TPEX",
   "price": 177.5,
   "pct1": 1.14,
   "amount": 1.67
  },
  "8261": {
   "market": "TWSE",
   "price": 195.5,
   "pct1": 9.83,
   "amount": 27.22
  },
  "8299": {
   "market": "TPEX",
   "price": 2305.0,
   "pct1": -2.95,
   "amount": 57.75
  },
  "8358": {
   "market": "TPEX",
   "price": 625.0,
   "pct1": -1.11,
   "amount": 5.67
  },
  "8374": {
   "market": "TWSE",
   "price": 90.0,
   "pct1": 0.0,
   "amount": 0.2
  },
  "8473": {
   "market": "TWSE",
   "price": 50.6,
   "pct1": 2.22,
   "amount": 0.42
  },
  "8996": {
   "market": "TWSE",
   "price": 1515.0,
   "pct1": 9.78,
   "amount": 64.59
  },
  "9802": {
   "market": "TWSE",
   "price": 78.5,
   "pct1": 1.03,
   "amount": 0.28
  },
  "9904": {
   "market": "TWSE",
   "price": 26.6,
   "pct1": 1.53,
   "amount": 3.53
  },
  "9910": {
   "market": "TWSE",
   "price": 73.6,
   "pct1": -5.64,
   "amount": 2.64
  },
  "9914": {
   "market": "TWSE",
   "price": 73.1,
   "pct1": -1.35,
   "amount": 0.72
  },
  "9919": {
   "market": "TWSE",
   "price": 14.1,
   "pct1": -0.35,
   "amount": 0.03
  },
  "9921": {
   "market": "TWSE",
   "price": 75.3,
   "pct1": -1.83,
   "amount": 0.92
  },
  "9941": {
   "market": "TWSE",
   "price": 82.3,
   "pct1": 0.86,
   "amount": 0.73
  }
 }
}