{
 "updated": "2026-06-23 09:48:02",
 "quotes": {
  "0050": {
   "market": "TWSE",
   "price": 111.25,
   "pct1": 0.09,
   "amount": 39.1
  },
  "1216": {
   "market": "TWSE",
   "price": 74.2,
   "pct1": -0.13,
   "amount": 1.19
  },
  "1301": {
   "market": "TWSE",
   "price": 51.0,
   "pct1": -2.67,
   "amount": 5.58
  },
  "1303": {
   "market": "TWSE",
   "price": 161.0,
   "pct1": 5.57,
   "amount": 135.54
  },
  "1409": {
   "market": "TWSE",
   "price": 28.75,
   "pct1": 2.13,
   "amount": 9.18
  },
  "1417": {
   "market": "TWSE",
   "price": 8.4,
   "pct1": -0.36,
   "amount": 0.0
  },
  "1466": {
   "market": "TWSE",
   "price": 14.5,
   "pct1": -1.02,
   "amount": 0.01
  },
  "1474": {
   "market": "TWSE",
   "price": 10.05,
   "pct1": -0.99,
   "amount": 0.0
  },
  "1476": {
   "market": "TWSE",
   "price": 313.5,
   "pct1": -1.1,
   "amount": 1.23
  },
  "1503": {
   "market": "TWSE",
   "price": 243.5,
   "pct1": -0.61,
   "amount": 5.78
  },
  "1504": {
   "market": "TWSE",
   "price": 71.9,
   "pct1": -0.42,
   "amount": 3.05
  },
  "1513": {
   "market": "TWSE",
   "price": 179.5,
   "pct1": -0.83,
   "amount": 9.05
  },
  "1514": {
   "market": "TWSE",
   "price": 125.5,
   "pct1": -1.18,
   "amount": 4.36
  },
  "1519": {
   "market": "TWSE",
   "price": 824.0,
   "pct1": -0.84,
   "amount": 5.11
  },
  "1536": {
   "market": "TWSE",
   "price": 49.45,
   "pct1": -4.17,
   "amount": 0.5
  },
  "1560": {
   "market": "TWSE",
   "price": 700.0,
   "pct1": -1.82,
   "amount": 1.7
  },
  "1590": {
   "market": "TWSE",
   "price": 1385.0,
   "pct1": -0.72,
   "amount": 3.88
  },
  "1597": {
   "market": "TWSE",
   "price": 152.5,
   "pct1": -3.17,
   "amount": 0.47
  },
  "1603": {
   "market": "TWSE",
   "price": 31.3,
   "pct1": -0.79,
   "amount": 0.02
  },
  "1604": {
   "market": "TWSE",
   "price": 23.2,
   "pct1": 0.22,
   "amount": 0.01
  },
  "1605": {
   "market": "TWSE",
   "price": 39.3,
   "pct1": -3.56,
   "amount": 8.47
  },
  "1609": {
   "market": "TWSE",
   "price": 37.7,
   "pct1": -2.46,
   "amount": 0.79
  },
  "1611": {
   "market": "TWSE",
   "price": 13.45,
   "pct1": 0.37,
   "amount": 0.02
  },
  "1612": {
   "market": "TWSE",
   "price": 37.7,
   "pct1": -1.44,
   "amount": 0.13
  },
  "1615": {
   "market": "TWSE",
   "price": 45.0,
   "pct1": -0.33,
   "amount": 0.0
  },
  "1626": {
   "market": "TWSE",
   "price": 9.71,
   "pct1": -0.31,
   "amount": 0.0
  },
  "1784": {
   "market": "TPEX",
   "price": 66.3,
   "pct1": -0.6,
   "amount": 0.01
  },
  "1815": {
   "market": "TPEX",
   "price": 104.5,
   "pct1": -1.88,
   "amount": 20.65
  },
  "2002": {
   "market": "TWSE",
   "price": 19.35,
   "pct1": -0.77,
   "amount": 7.94
  },
  "2049": {
   "market": "TWSE",
   "price": 342.0,
   "pct1": -0.44,
   "amount": 2.14
  },
  "2059": {
   "market": "TWSE",
   "price": 7260.0,
   "pct1": -3.84,
   "amount": 8.75
  },
  "2207": {
   "market": "TWSE",
   "price": 487.0,
   "pct1": 1.25,
   "amount": 0.73
  },
  "2208": {
   "market": "TWSE",
   "price": 17.7,
   "pct1": -1.67,
   "amount": 0.17
  },
  "2231": {
   "market": "TWSE",
   "price": 92.6,
   "pct1": -1.8,
   "amount": 0.06
  },
  "2233": {
   "market": "TWSE",
   "price": 284.0,
   "pct1": -9.98,
   "amount": 4.55
  },
  "2236": {
   "market": "TWSE",
   "price": 134.5,
   "pct1": -1.82,
   "amount": 0.07
  },
  "2301": {
   "market": "TWSE",
   "price": 236.5,
   "pct1": 2.16,
   "amount": 47.71
  },
  "2303": {
   "market": "TWSE",
   "price": 172.5,
   "pct1": 7.81,
   "amount": 417.58
  },
  "2308": {
   "market": "TWSE",
   "price": 2130.0,
   "pct1": -0.93,
   "amount": 69.06
  },
  "2313": {
   "market": "TWSE",
   "price": 251.5,
   "pct1": -3.08,
   "amount": 26.17
  },
  "2317": {
   "market": "TWSE",
   "price": 265.0,
   "pct1": -1.3,
   "amount": 57.15
  },
  "2324": {
   "market": "TWSE",
   "price": 37.1,
   "pct1": -1.07,
   "amount": 5.45
  },
  "2327": {
   "market": "TWSE",
   "price": 1030.0,
   "pct1": -3.29,
   "amount": 174.26
  },
  "2329": {
   "market": "TWSE",
   "price": 57.0,
   "pct1": -2.56,
   "amount": 2.11
  },
  "2330": {
   "market": "TWSE",
   "price": 2515.0,
   "pct1": 0.2,
   "amount": 224.79
  },
  "2337": {
   "market": "TWSE",
   "price": 180.5,
   "pct1": -2.7,
   "amount": 146.86
  },
  "2344": {
   "market": "TWSE",
   "price": 212.0,
   "pct1": -4.5,
   "amount": 156.62
  },
  "2345": {
   "market": "TWSE",
   "price": 2525.0,
   "pct1": -2.7,
   "amount": 38.55
  },
  "2353": {
   "market": "TWSE",
   "price": 33.8,
   "pct1": -0.59,
   "amount": 2.61
  },
  "2355": {
   "market": "TWSE",
   "price": 57.1,
   "pct1": -2.73,
   "amount": 1.63
  },
  "2356": {
   "market": "TWSE",
   "price": 66.8,
   "pct1": -1.47,
   "amount": 5.84
  },
  "2357": {
   "market": "TWSE",
   "price": 802.0,
   "pct1": 1.78,
   "amount": 16.45
  },
  "2359": {
   "market": "TWSE",
   "price": 136.0,
   "pct1": -0.37,
   "amount": 1.04
  },
  "2360": {
   "market": "TWSE",
   "price": 2320.0,
   "pct1": 0.43,
   "amount": 4.69
  },
  "2367": {
   "market": "TWSE",
   "price": 59.1,
   "pct1": -2.48,
   "amount": 4.45
  },
  "2368": {
   "market": "TWSE",
   "price": 1315.0,
   "pct1": -5.73,
   "amount": 21.68
  },
  "2371": {
   "market": "TWSE",
   "price": 27.9,
   "pct1": -0.89,
   "amount": 0.6
  },
  "2375": {
   "market": "TWSE",
   "price": 207.5,
   "pct1": -5.25,
   "amount": 11.32
  },
  "2376": {
   "market": "TWSE",
   "price": 333.5,
   "pct1": -1.77,
   "amount": 7.65
  },
  "2377": {
   "market": "TWSE",
   "price": 134.0,
   "pct1": -2.19,
   "amount": 4.15
  },
  "2379": {
   "market": "TWSE",
   "price": 925.0,
   "pct1": 2.78,
   "amount": 22.06
  },
  "2382": {
   "market": "TWSE",
   "price": 372.5,
   "pct1": -1.97,
   "amount": 13.84
  },
  "2383": {
   "market": "TWSE",
   "price": 5630.0,
   "pct1": -3.35,
   "amount": 11.0
  },
  "2395": {
   "market": "TWSE",
   "price": 494.0,
   "pct1": -1.1,
   "amount": 2.04
  },
  "2397": {
   "market": "TWSE",
   "price": 60.0,
   "pct1": -2.6,
   "amount": 0.09
  },
  "2401": {
   "market": "TWSE",
   "price": 33.2,
   "pct1": -2.35,
   "amount": 1.61
  },
  "2404": {
   "market": "TWSE",
   "price": 1265.0,
   "pct1": -1.17,
   "amount": 8.69
  },
  "2408": {
   "market": "TWSE",
   "price": 477.0,
   "pct1": -5.54,
   "amount": 231.44
  },
  "2409": {
   "market": "TWSE",
   "price": 32.05,
   "pct1": 3.55,
   "amount": 112.2
  },
  "2412": {
   "market": "TWSE",
   "price": 145.0,
   "pct1": 0.35,
   "amount": 1.38
  },
  "2413": {
   "market": "TWSE",
   "price": 53.9,
   "pct1": -4.94,
   "amount": 0.83
  },
  "2419": {
   "market": "TWSE",
   "price": 29.1,
   "pct1": -1.19,
   "amount": 0.1
  },
  "2421": {
   "market": "TWSE",
   "price": 148.0,
   "pct1": -1.33,
   "amount": 1.38
  },
  "2428": {
   "market": "TWSE",
   "price": 307.0,
   "pct1": -1.29,
   "amount": 1.83
  },
  "2429": {
   "market": "TWSE",
   "price": 39.75,
   "pct1": -6.03,
   "amount": 0.21
  },
  "2436": {
   "market": "TWSE",
   "price": 78.8,
   "pct1": 0.25,
   "amount": 5.46
  },
  "2449": {
   "market": "TWSE",
   "price": 343.0,
   "pct1": 1.18,
   "amount": 104.05
  },
  "2451": {
   "market": "TWSE",
   "price": 302.5,
   "pct1": -2.26,
   "amount": 3.98
  },
  "2453": {
   "market": "TWSE",
   "price": 56.9,
   "pct1": -1.04,
   "amount": 0.09
  },
  "2454": {
   "market": "TWSE",
   "price": 4600.0,
   "pct1": 3.02,
   "amount": 249.31
  },
  "2455": {
   "market": "TWSE",
   "price": 390.0,
   "pct1": -4.76,
   "amount": 0.85
  },
  "2464": {
   "market": "TWSE",
   "price": 169.5,
   "pct1": -2.02,
   "amount": 5.68
  },
  "2467": {
   "market": "TWSE",
   "price": 594.0,
   "pct1": -5.71,
   "amount": 3.63
  },
  "2471": {
   "market": "TWSE",
   "price": 53.7,
   "pct1": 0.0,
   "amount": 0.01
  },
  "2472": {
   "market": "TWSE",
   "price": 378.5,
   "pct1": -3.81,
   "amount": 12.48
  },
  "2474": {
   "market": "TWSE",
   "price": 216.5,
   "pct1": 5.1,
   "amount": 13.26
  },
  "2478": {
   "market": "TWSE",
   "price": 226.0,
   "pct1": -4.03,
   "amount": 0.5
  },
  "2480": {
   "market": "TWSE",
   "price": 152.0,
   "pct1": -1.62,
   "amount": 0.08
  },
  "2481": {
   "market": "TWSE",
   "price": 193.5,
   "pct1": 9.94,
   "amount": 109.5
  },
  "2489": {
   "market": "TWSE",
   "price": 49.15,
   "pct1": -3.06,
   "amount": 7.15
  },
  "2492": {
   "market": "TWSE",
   "price": 593.0,
   "pct1": -3.89,
   "amount": 78.23
  },
  "2603": {
   "market": "TWSE",
   "price": 191.5,
   "pct1": -0.78,
   "amount": 7.5
  },
  "2609": {
   "market": "TWSE",
   "price": 51.9,
   "pct1": -0.76,
   "amount": 1.62
  },
  "2610": {
   "market": "TWSE",
   "price": 21.8,
   "pct1": 0.0,
   "amount": 1.93
  },
  "2615": {
   "market": "TWSE",
   "price": 80.0,
   "pct1": -0.62,
   "amount": 1.14
  },
  "2618": {
   "market": "TWSE",
   "price": 41.8,
   "pct1": 0.36,
   "amount": 3.34
  },
  "2630": {
   "market": "TWSE",
   "price": 42.65,
   "pct1": -0.58,
   "amount": 0.23
  },
  "2634": {
   "market": "TWSE",
   "price": 49.95,
   "pct1": -0.3,
   "amount": 1.98
  },
  "2637": {
   "market": "TWSE",
   "price": 77.0,
   "pct1": -0.13,
   "amount": 0.23
  },
  "2644": {
   "market": "TPEX",
   "price": 85.0,
   "pct1": 1.19,
   "amount": 0.01
  },
  "2645": {
   "market": "TWSE",
   "price": 172.0,
   "pct1": -0.86,
   "amount": 0.5
  },
  "2706": {
   "market": "TWSE",
   "price": 12.6,
   "pct1": 0.8,
   "amount": 0.0
  },
  "2723": {
   "market": "TWSE",
   "price": 65.6,
   "pct1": -0.76,
   "amount": 0.04
  },
  "2727": {
   "market": "TWSE",
   "price": 246.0,
   "pct1": -0.2,
   "amount": 0.12
  },
  "2731": {
   "market": "TWSE",
   "price": 151.5,
   "pct1": 0.0,
   "amount": 0.22
  },
  "2881": {
   "market": "TWSE",
   "price": 140.0,
   "pct1": 1.08,
   "amount": 4.27
  },
  "2882": {
   "market": "TWSE",
   "price": 114.5,
   "pct1": 1.33,
   "amount": 3.41
  },
  "2884": {
   "market": "TWSE",
   "price": 35.85,
   "pct1": 0.14,
   "amount": 2.94
  },
  "2886": {
   "market": "TWSE",
   "price": 44.75,
   "pct1": 0.0,
   "amount": 1.0
  },
  "2891": {
   "market": "TWSE",
   "price": 71.5,
   "pct1": 1.42,
   "amount": 5.35
  },
  "2912": {
   "market": "TWSE",
   "price": 223.0,
   "pct1": 0.9,
   "amount": 0.44
  },
  "2929": {
   "market": "TWSE",
   "price": 5.9,
   "pct1": -1.67,
   "amount": 0.0
  },
  "2949": {
   "market": "TPEX",
   "price": 68.7,
   "pct1": 0.0,
   "amount": 0.01
  },
  "3005": {
   "market": "TWSE",
   "price": 100.0,
   "pct1": -0.5,
   "amount": 1.3
  },
  "3006": {
   "market": "TWSE",
   "price": 262.5,
   "pct1": 3.35,
   "amount": 25.4
  },
  "3008": {
   "market": "TWSE",
   "price": 5080.0,
   "pct1": -2.03,
   "amount": 26.52
  },
  "3013": {
   "market": "TWSE",
   "price": 111.5,
   "pct1": -1.76,
   "amount": 0.45
  },
  "3014": {
   "market": "TWSE",
   "price": 161.5,
   "pct1": 0.62,
   "amount": 1.36
  },
  "3016": {
   "market": "TWSE",
   "price": 152.5,
   "pct1": 9.71,
   "amount": 8.22
  },
  "3017": {
   "market": "TWSE",
   "price": 2415.0,
   "pct1": -0.21,
   "amount": 16.42
  },
  "3022": {
   "market": "TWSE",
   "price": 81.6,
   "pct1": -1.92,
   "amount": 0.2
  },
  "3024": {
   "market": "TWSE",
   "price": 12.3,
   "pct1": -1.6,
   "amount": 0.03
  },
  "3026": {
   "market": "TWSE",
   "price": 840.0,
   "pct1": -6.35,
   "amount": 2.29
  },
  "3027": {
   "market": "TWSE",
   "price": 21.45,
   "pct1": -0.46,
   "amount": 0.04
  },
  "3029": {
   "market": "TWSE",
   "price": 100.0,
   "pct1": -1.48,
   "amount": 0.22
  },
  "3030": {
   "market": "TWSE",
   "price": 340.0,
   "pct1": -2.86,
   "amount": 1.77
  },
  "3032": {
   "market": "TWSE",
   "price": 84.1,
   "pct1": -1.06,
   "amount": 0.12
  },
  "3034": {
   "market": "TWSE",
   "price": 577.0,
   "pct1": 1.76,
   "amount": 33.42
  },
  "3035": {
   "market": "TWSE",
   "price": 242.0,
   "pct1": 5.45,
   "amount": 33.4
  },
  "3036": {
   "market": "TWSE",
   "price": 226.0,
   "pct1": 0.44,
   "amount": 5.65
  },
  "3037": {
   "market": "TWSE",
   "price": 1050.0,
   "pct1": 4.48,
   "amount": 75.68
  },
  "3044": {
   "market": "TWSE",
   "price": 560.0,
   "pct1": -1.06,
   "amount": 3.71
  },
  "3060": {
   "market": "TWSE",
   "price": 40.6,
   "pct1": -2.52,
   "amount": 2.02
  },
  "3081": {
   "market": "TPEX",
   "price": 2360.0,
   "pct1": -0.63,
   "amount": 13.03
  },
  "3088": {
   "market": "TPEX",
   "price": 142.0,
   "pct1": -1.39,
   "amount": 0.29
  },
  "3105": {
   "market": "TPEX",
   "price": 543.0,
   "pct1": 0.37,
   "amount": 37.07
  },
  "3131": {
   "market": "TPEX",
   "price": 3430.0,
   "pct1": -4.32,
   "amount": 3.53
  },
  "3163": {
   "market": "TPEX",
   "price": 872.0,
   "pct1": 0.23,
   "amount": 1.64
  },
  "3167": {
   "market": "TWSE",
   "price": 805.0,
   "pct1": 0.0,
   "amount": 0.34
  },
  "3189": {
   "market": "TWSE",
   "price": 763.0,
   "pct1": -4.15,
   "amount": 74.09
  },
  "3231": {
   "market": "TWSE",
   "price": 159.5,
   "pct1": -1.85,
   "amount": 15.59
  },
  "3260": {
   "market": "TPEX",
   "price": 421.0,
   "pct1": -3.0,
   "amount": 17.54
  },
  "3324": {
   "market": "TPEX",
   "price": 1055.0,
   "pct1": -1.86,
   "amount": 5.97
  },
  "3357": {
   "market": "TPEX",
   "price": 328.0,
   "pct1": -5.34,
   "amount": 8.63
  },
  "3363": {
   "market": "TPEX",
   "price": 715.0,
   "pct1": 0.42,
   "amount": 5.33
  },
  "3376": {
   "market": "TWSE",
   "price": 205.0,
   "pct1": -1.91,
   "amount": 2.6
  },
  "3402": {
   "market": "TPEX",
   "price": 141.5,
   "pct1": -0.35,
   "amount": 0.15
  },
  "3413": {
   "market": "TWSE",
   "price": 315.5,
   "pct1": -1.71,
   "amount": 1.72
  },
  "3416": {
   "market": "TWSE",
   "price": 173.5,
   "pct1": -2.25,
   "amount": 0.11
  },
  "3443": {
   "market": "TWSE",
   "price": 4670.0,
   "pct1": -1.79,
   "amount": 29.43
  },
  "3450": {
   "market": "TWSE",
   "price": 569.0,
   "pct1": 2.15,
   "amount": 21.86
  },
  "3479": {
   "market": "TPEX",
   "price": 132.5,
   "pct1": -1.85,
   "amount": 0.29
  },
  "3481": {
   "market": "TWSE",
   "price": 68.7,
   "pct1": 4.09,
   "amount": 176.06
  },
  "3483": {
   "market": "TPEX",
   "price": 92.8,
   "pct1": -2.01,
   "amount": 0.11
  },
  "3491": {
   "market": "TPEX",
   "price": 1395.0,
   "pct1": -5.1,
   "amount": 15.99
  },
  "3515": {
   "market": "TWSE",
   "price": 244.0,
   "pct1": -0.81,
   "amount": 0.25
  },
  "3530": {
   "market": "TWSE",
   "price": 72.8,
   "pct1": -0.82,
   "amount": 0.08
  },
  "3551": {
   "market": "TPEX",
   "price": 204.5,
   "pct1": -3.76,
   "amount": 0.49
  },
  "3556": {
   "market": "TPEX",
   "price": 74.0,
   "pct1": -2.37,
   "amount": 0.48
  },
  "3558": {
   "market": "TPEX",
   "price": 131.5,
   "pct1": -1.5,
   "amount": 0.03
  },
  "3564": {
   "market": "TPEX",
   "price": 46.5,
   "pct1": -1.8,
   "amount": 0.03
  },
  "3583": {
   "market": "TWSE",
   "price": 876.0,
   "pct1": -1.46,
   "amount": 3.72
  },
  "3594": {
   "market": "TPEX",
   "price": 48.7,
   "pct1": 1.46,
   "amount": 0.06
  },
  "3596": {
   "market": "TWSE",
   "price": 189.0,
   "pct1": 0.53,
   "amount": 0.77
  },
  "3653": {
   "market": "TWSE",
   "price": 3865.0,
   "pct1": 0.65,
   "amount": 10.2
  },
  "3661": {
   "market": "TWSE",
   "price": 4260.0,
   "pct1": -1.5,
   "amount": 18.02
  },
  "3665": {
   "market": "TWSE",
   "price": 1995.0,
   "pct1": 0.25,
   "amount": 7.1
  },
  "3673": {
   "market": "TWSE",
   "price": 88.3,
   "pct1": -0.23,
   "amount": 5.66
  },
  "3680": {
   "market": "TPEX",
   "price": 536.0,
   "pct1": -2.01,
   "amount": 1.65
  },
  "3686": {
   "market": "TWSE",
   "price": 17.05,
   "pct1": -0.58,
   "amount": 0.01
  },
  "3693": {
   "market": "TPEX",
   "price": 499.0,
   "pct1": -2.73,
   "amount": 0.99
  },
  "3702": {
   "market": "TWSE",
   "price": 112.0,
   "pct1": -0.44,
   "amount": 1.02
  },
  "3704": {
   "market": "TWSE",
   "price": 49.8,
   "pct1": 2.68,
   "amount": 1.17
  },
  "3706": {
   "market": "TWSE",
   "price": 86.2,
   "pct1": -1.37,
   "amount": 3.36
  },
  "3707": {
   "market": "TPEX",
   "price": 100.5,
   "pct1": 9.84,
   "amount": 27.54
  },
  "3711": {
   "market": "TWSE",
   "price": 688.0,
   "pct1": 2.08,
   "amount": 98.73
  },
  "4540": {
   "market": "TWSE",
   "price": 59.9,
   "pct1": -3.54,
   "amount": 0.36
  },
  "4541": {
   "market": "TPEX",
   "price": 49.75,
   "pct1": -2.45,
   "amount": 0.16
  },
  "4576": {
   "market": "TWSE",
   "price": 227.0,
   "pct1": -3.81,
   "amount": 1.67
  },
  "4585": {
   "market": "TWSE",
   "price": 312.5,
   "pct1": -0.48,
   "amount": 0.19
  },
  "4749": {
   "market": "TPEX",
   "price": 942.0,
   "pct1": -2.48,
   "amount": 4.56
  },
  "4763": {
   "market": "TWSE",
   "price": 47.1,
   "pct1": 3.29,
   "amount": 3.53
  },
  "4772": {
   "market": "TPEX",
   "price": 279.5,
   "pct1": -1.24,
   "amount": 0.48
  },
  "4906": {
   "market": "TWSE",
   "price": 46.8,
   "pct1": -1.78,
   "amount": 4.26
  },
  "4916": {
   "market": "TWSE",
   "price": 101.0,
   "pct1": -3.81,
   "amount": 2.11
  },
  "4938": {
   "market": "TWSE",
   "price": 80.9,
   "pct1": -1.34,
   "amount": 3.59
  },
  "4943": {
   "market": "TWSE",
   "price": 8.66,
   "pct1": 0.0,
   "amount": 0.0
  },
  "4953": {
   "market": "TPEX",
   "price": 130.0,
   "pct1": -1.89,
   "amount": 0.35
  },
  "4958": {
   "market": "TWSE",
   "price": 598.0,
   "pct1": -3.86,
   "amount": 82.29
  },
  "4961": {
   "market": "TWSE",
   "price": 180.0,
   "pct1": 1.41,
   "amount": 2.35
  },
  "4966": {
   "market": "TPEX",
   "price": 678.0,
   "pct1": -2.45,
   "amount": 3.3
  },
  "4967": {
   "market": "TWSE",
   "price": 279.0,
   "pct1": -1.93,
   "amount": 4.72
  },
  "4971": {
   "market": "TPEX",
   "price": 568.0,
   "pct1": -0.53,
   "amount": 2.87
  },
  "4977": {
   "market": "TWSE",
   "price": 187.5,
   "pct1": -1.83,
   "amount": 1.43
  },
  "4979": {
   "market": "TPEX",
   "price": 547.0,
   "pct1": -0.91,
   "amount": 8.48
  },
  "5222": {
   "market": "TWSE",
   "price": 120.5,
   "pct1": -3.6,
   "amount": 0.37
  },
  "5258": {
   "market": "TWSE",
   "price": 50.5,
   "pct1": -1.56,
   "amount": 0.04
  },
  "5269": {
   "market": "TWSE",
   "price": 1425.0,
   "pct1": -1.72,
   "amount": 2.35
  },
  "5274": {
   "market": "TPEX",
   "price": 19000.0,
   "pct1": -1.43,
   "amount": 7.65
  },
  "5285": {
   "market": "TWSE",
   "price": 105.0,
   "pct1": 2.44,
   "amount": 4.89
  },
  "5289": {
   "market": "TPEX",
   "price": 1910.0,
   "pct1": -3.05,
   "amount": 15.18
  },
  "5299": {
   "market": "TPEX",
   "price": 133.0,
   "pct1": 3.1,
   "amount": 4.22
  },
  "5328": {
   "market": "TPEX",
   "price": 55.8,
   "pct1": -3.79,
   "amount": 4.04
  },
  "5340": {
   "market": "TPEX",
   "price": 98.5,
   "pct1": -0.51,
   "amount": 2.71
  },
  "5347": {
   "market": "TPEX",
   "price": 186.0,
   "pct1": -2.87,
   "amount": 34.36
  },
  "5371": {
   "market": "TPEX",
   "price": 75.5,
   "pct1": 1.21,
   "amount": 2.73
  },
  "5388": {
   "market": "TWSE",
   "price": 82.0,
   "pct1": -0.49,
   "amount": 0.55
  },
  "5439": {
   "market": "TPEX",
   "price": 331.0,
   "pct1": -1.49,
   "amount": 1.39
  },
  "5443": {
   "market": "TPEX",
   "price": 107.5,
   "pct1": -3.15,
   "amount": 0.7
  },
  "5471": {
   "market": "TWSE",
   "price": 65.2,
   "pct1": 2.52,
   "amount": 2.43
  },
  "5474": {
   "market": "TPEX",
   "price": 179.0,
   "pct1": -0.28,
   "amount": 0.15
  },
  "5536": {
   "market": "TPEX",
   "price": 1250.0,
   "pct1": -2.34,
   "amount": 2.69
  },
  "5706": {
   "market": "TWSE",
   "price": 53.2,
   "pct1": -1.66,
   "amount": 0.05
  },
  "5871": {
   "market": "TWSE",
   "price": 117.0,
   "pct1": -0.85,
   "amount": 0.76
  },
  "5903": {
   "market": "TPEX",
   "price": 188.0,
   "pct1": -0.53,
   "amount": 0.01
  },
  "6112": {
   "market": "TWSE",
   "price": 44.75,
   "pct1": -1.43,
   "amount": 0.08
  },
  "6116": {
   "market": "TWSE",
   "price": 20.2,
   "pct1": 1.25,
   "amount": 17.55
  },
  "6117": {
   "market": "TWSE",
   "price": 76.2,
   "pct1": -1.3,
   "amount": 0.08
  },
  "6121": {
   "market": "TPEX",
   "price": 419.5,
   "pct1": -1.06,
   "amount": 0.38
  },
  "6125": {
   "market": "TPEX",
   "price": 61.8,
   "pct1": -1.28,
   "amount": 0.25
  },
  "6128": {
   "market": "TWSE",
   "price": 20.4,
   "pct1": -0.97,
   "amount": 0.01
  },
  "6138": {
   "market": "TPEX",
   "price": 389.5,
   "pct1": -1.14,
   "amount": 7.36
  },
  "6139": {
   "market": "TWSE",
   "price": 797.0,
   "pct1": -1.6,
   "amount": 7.84
  },
  "6146": {
   "market": "TPEX",
   "price": 190.0,
   "pct1": -1.81,
   "amount": 0.18
  },
  "6147": {
   "market": "TPEX",
   "price": 269.0,
   "pct1": -2.89,
   "amount": 60.67
  },
  "6155": {
   "market": "TWSE",
   "price": 92.6,
   "pct1": -4.24,
   "amount": 4.35
  },
  "6163": {
   "market": "TPEX",
   "price": 50.0,
   "pct1": -1.96,
   "amount": 0.14
  },
  "6166": {
   "market": "TWSE",
   "price": 155.0,
   "pct1": -1.9,
   "amount": 1.12
  },
  "6168": {
   "market": "TWSE",
   "price": 33.8,
   "pct1": 8.68,
   "amount": 2.97
  },
  "6173": {
   "market": "TPEX",
   "price": 290.5,
   "pct1": -4.91,
   "amount": 0.82
  },
  "6182": {
   "market": "TPEX",
   "price": 112.0,
   "pct1": -3.86,
   "amount": 25.31
  },
  "6187": {
   "market": "TPEX",
   "price": 1200.0,
   "pct1": -4.76,
   "amount": 2.47
  },
  "6188": {
   "market": "TPEX",
   "price": 78.4,
   "pct1": -1.13,
   "amount": 0.29
  },
  "6196": {
   "market": "TWSE",
   "price": 546.0,
   "pct1": -2.85,
   "amount": 2.09
  },
  "6202": {
   "market": "TWSE",
   "price": 72.4,
   "pct1": -1.76,
   "amount": 8.93
  },
  "6206": {
   "market": "TWSE",
   "price": 133.0,
   "pct1": -1.12,
   "amount": 0.21
  },
  "6213": {
   "market": "TWSE",
   "price": 305.0,
   "pct1": -0.97,
   "amount": 34.89
  },
  "6214": {
   "market": "TWSE",
   "price": 132.5,
   "pct1": -6.03,
   "amount": 1.46
  },
  "6223": {
   "market": "TPEX",
   "price": 6500.0,
   "pct1": 1.17,
   "amount": 13.49
  },
  "6239": {
   "market": "TWSE",
   "price": 350.5,
   "pct1": -4.23,
   "amount": 59.35
  },
  "6244": {
   "market": "TPEX",
   "price": 28.15,
   "pct1": -1.57,
   "amount": 0.33
  },
  "6245": {
   "market": "TPEX",
   "price": 81.5,
   "pct1": -0.73,
   "amount": 0.11
  },
  "6263": {
   "market": "TPEX",
   "price": 159.0,
   "pct1": -2.45,
   "amount": 0.13
  },
  "6271": {
   "market": "TWSE",
   "price": 259.0,
   "pct1": -2.81,
   "amount": 20.38
  },
  "6274": {
   "market": "TPEX",
   "price": 1810.0,
   "pct1": -4.74,
   "amount": 32.42
  },
  "6278": {
   "market": "TWSE",
   "price": 205.5,
   "pct1": -0.24,
   "amount": 1.96
  },
  "6282": {
   "market": "TWSE",
   "price": 62.9,
   "pct1": -1.56,
   "amount": 16.37
  },
  "6285": {
   "market": "TWSE",
   "price": 258.0,
   "pct1": -3.73,
   "amount": 15.1
  },
  "6414": {
   "market": "TWSE",
   "price": 376.0,
   "pct1": -1.31,
   "amount": 1.14
  },
  "6415": {
   "market": "TWSE",
   "price": 679.0,
   "pct1": 0.89,
   "amount": 23.2
  },
  "6416": {
   "market": "TWSE",
   "price": 83.2,
   "pct1": 0.0,
   "amount": 0.02
  },
  "6435": {
   "market": "TPEX",
   "price": 374.5,
   "pct1": 7.31,
   "amount": 6.84
  },
  "6442": {
   "market": "TWSE",
   "price": 2085.0,
   "pct1": 0.0,
   "amount": 31.43
  },
  "6443": {
   "market": "TWSE",
   "price": 37.9,
   "pct1": -2.82,
   "amount": 1.57
  },
  "6451": {
   "market": "TWSE",
   "price": 629.0,
   "pct1": 1.94,
   "amount": 21.05
  },
  "6485": {
   "market": "TPEX",
   "price": 88.7,
   "pct1": -2.42,
   "amount": 0.3
  },
  "6488": {
   "market": "TPEX",
   "price": 1055.0,
   "pct1": -5.38,
   "amount": 1.29
  },
  "6510": {
   "market": "TPEX",
   "price": 3570.0,
   "pct1": 1.28,
   "amount": 6.45
  },
  "6515": {
   "market": "TWSE",
   "price": 9430.0,
   "pct1": -0.32,
   "amount": 4.82
  },
  "6531": {
   "market": "TWSE",
   "price": 1140.0,
   "pct1": 2.24,
   "amount": 39.64
  },
  "6561": {
   "market": "TPEX",
   "price": 340.0,
   "pct1": -0.58,
   "amount": 0.04
  },
  "6569": {
   "market": "TPEX",
   "price": 111.5,
   "pct1": -0.89,
   "amount": 0.0
  },
  "6570": {
   "market": "TPEX",
   "price": 54.3,
   "pct1": -1.09,
   "amount": 0.03
  },
  "6573": {
   "market": "TWSE",
   "price": 19.25,
   "pct1": 8.15,
   "amount": 0.42
  },
  "6640": {
   "market": "TPEX",
   "price": 1080.0,
   "pct1": -1.82,
   "amount": 0.62
  },
  "6643": {
   "market": "TPEX",
   "price": 497.0,
   "pct1": -0.6,
   "amount": 0.58
  },
  "6667": {
   "market": "TPEX",
   "price": 277.0,
   "pct1": -5.14,
   "amount": 1.58
  },
  "6669": {
   "market": "TWSE",
   "price": 4710.0,
   "pct1": -2.99,
   "amount": 22.92
  },
  "6680": {
   "market": "TPEX",
   "price": 51.7,
   "pct1": 0.0,
   "amount": 0.01
  },
  "6689": {
   "market": "TWSE",
   "price": 66.8,
   "pct1": -0.3,
   "amount": 0.02
  },
  "6690": {
   "market": "TPEX",
   "price": 177.0,
   "pct1": -1.39,
   "amount": 0.05
  },
  "6691": {
   "market": "TWSE",
   "price": 720.0,
   "pct1": -1.1,
   "amount": 0.96
  },
  "6739": {
   "market": "TPEX",
   "price": 1185.0,
   "pct1": -0.42,
   "amount": 0.9
  },
  "6753": {
   "market": "TWSE",
   "price": 126.0,
   "pct1": -1.56,
   "amount": 0.47
  },
  "6770": {
   "market": "TWSE",
   "price": 83.0,
   "pct1": 1.72,
   "amount": 177.74
  },
  "6788": {
   "market": "TPEX",
   "price": 436.0,
   "pct1": -1.69,
   "amount": 1.22
  },
  "6789": {
   "market": "TWSE",
   "price": 562.0,
   "pct1": 1.26,
   "amount": 10.09
  },
  "6805": {
   "market": "TWSE",
   "price": 1785.0,
   "pct1": -1.92,
   "amount": 3.55
  },
  "6811": {
   "market": "TPEX",
   "price": 227.5,
   "pct1": -0.66,
   "amount": 0.11
  },
  "6829": {
   "market": "TPEX",
   "price": 204.5,
   "pct1": -1.45,
   "amount": 0.46
  },
  "6857": {
   "market": "TPEX",
   "price": 94.3,
   "pct1": 0.0,
   "amount": 0.0
  },
  "6870": {
   "market": "TPEX",
   "price": 271.0,
   "pct1": 0.37,
   "amount": 0.09
  },
  "7703": {
   "market": "TPEX",
   "price": 205.5,
   "pct1": -3.52,
   "amount": 0.11
  },
  "7717": {
   "market": "TPEX",
   "price": 521.0,
   "pct1": -4.23,
   "amount": 0.5
  },
  "7719": {
   "market": "TPEX",
   "price": 40.0,
   "pct1": -6.21,
   "amount": 0.1
  },
  "7750": {
   "market": "TWSE",
   "price": 2185.0,
   "pct1": -4.59,
   "amount": 2.65
  },
  "7769": {
   "market": "TWSE",
   "price": 6860.0,
   "pct1": -0.8,
   "amount": 6.78
  },
  "8016": {
   "market": "TWSE",
   "price": 322.5,
   "pct1": 2.38,
   "amount": 4.31
  },
  "8021": {
   "market": "TWSE",
   "price": 570.0,
   "pct1": -1.89,
   "amount": 0.74
  },
  "8028": {
   "market": "TWSE",
   "price": 316.5,
   "pct1": -1.86,
   "amount": 6.23
  },
  "8033": {
   "market": "TWSE",
   "price": 142.5,
   "pct1": 0.35,
   "amount": 6.57
  },
  "8038": {
   "market": "TPEX",
   "price": 40.15,
   "pct1": -2.31,
   "amount": 0.04
  },
  "8043": {
   "market": "TPEX",
   "price": 206.0,
   "pct1": -3.29,
   "amount": 9.88
  },
  "8044": {
   "market": "TPEX",
   "price": 30.5,
   "pct1": -2.56,
   "amount": 0.06
  },
  "8046": {
   "market": "TWSE",
   "price": 940.0,
   "pct1": 8.8,
   "amount": 157.8
  },
  "8048": {
   "market": "TPEX",
   "price": 66.9,
   "pct1": 0.15,
   "amount": 0.06
  },
  "8050": {
   "market": "TPEX",
   "price": 55.9,
   "pct1": -0.53,
   "amount": 0.08
  },
  "8069": {
   "market": "TPEX",
   "price": 199.5,
   "pct1": -1.72,
   "amount": 2.05
  },
  "8081": {
   "market": "TWSE",
   "price": 330.5,
   "pct1": -3.22,
   "amount": 2.93
  },
  "8086": {
   "market": "TPEX",
   "price": 164.5,
   "pct1": -0.6,
   "amount": 1.89
  },
  "8099": {
   "market": "TPEX",
   "price": 59.4,
   "pct1": -1.16,
   "amount": 0.0
  },
  "8101": {
   "market": "TWSE",
   "price": 13.75,
   "pct1": 0.0,
   "amount": 0.0
  },
  "8114": {
   "market": "TWSE",
   "price": 209.5,
   "pct1": -0.95,
   "amount": 0.45
  },
  "8121": {
   "market": "TPEX",
   "price": 51.8,
   "pct1": -4.78,
   "amount": 0.63
  },
  "8131": {
   "market": "TWSE",
   "price": 76.0,
   "pct1": -3.55,
   "amount": 2.79
  },
  "8210": {
   "market": "TWSE",
   "price": 1345.0,
   "pct1": -1.82,
   "amount": 2.13
  },
  "8222": {
   "market": "TWSE",
   "price": 36.1,
   "pct1": -2.17,
   "amount": 0.04
  },
  "8234": {
   "market": "TPEX",
   "price": 64.8,
   "pct1": -1.07,
   "amount": 0.1
  },
  "8255": {
   "market": "TPEX",
   "price": 216.0,
   "pct1": 0.7,
   "amount": 14.14
  },
  "8261": {
   "market": "TWSE",
   "price": 260.0,
   "pct1": 9.94,
   "amount": 39.26
  },
  "8299": {
   "market": "TPEX",
   "price": 2495.0,
   "pct1": -3.29,
   "amount": 57.57
  },
  "8358": {
   "market": "TPEX",
   "price": 697.0,
   "pct1": 0.87,
   "amount": 43.89
  },
  "8374": {
   "market": "TWSE",
   "price": 90.7,
   "pct1": -1.95,
   "amount": 0.11
  },
  "8473": {
   "market": "TWSE",
   "price": 50.0,
   "pct1": -1.57,
   "amount": 0.12
  },
  "8996": {
   "market": "TWSE",
   "price": 1475.0,
   "pct1": -5.14,
   "amount": 11.78
  },
  "9802": {
   "market": "TWSE",
   "price": 75.1,
   "pct1": -0.92,
   "amount": 0.06
  },
  "9904": {
   "market": "TWSE",
   "price": 26.1,
   "pct1": 0.0,
   "amount": 1.75
  },
  "9910": {
   "market": "TWSE",
   "price": 70.6,
   "pct1": -0.14,
   "amount": 0.28
  },
  "9914": {
   "market": "TWSE",
   "price": 71.7,
   "pct1": -2.32,
   "amount": 0.2
  },
  "9919": {
   "market": "TWSE",
   "price": 13.9,
   "pct1": 0.0,
   "amount": 0.02
  },
  "9921": {
   "market": "TWSE",
   "price": 74.1,
   "pct1": -1.85,
   "amount": 0.2
  },
  "9941": {
   "market": "TWSE",
   "price": 80.8,
   "pct1": -1.22,
   "amount": 0.36
  }
 }
}